{"textid":"P214772","corpus":"admin_oakk","title":"Ist L 06749 = ITT 5, 06749","period":"Old Akkadian","genre":"Administrative","subgenre":"","provenience":"Girsu","total_lines":10,"total_words":31,"lines":[{"line_label":"o 1","line_ref":"P214772.3","transliteration":"2(u) 6(a\u0161@c) {ge\u0161}u\u2083 x","gloss":"planking","word_count":4},{"line_label":"o 2","line_ref":"P214772.4","transliteration":"2(u) 1(a\u0161@c) {ge\u0161}u\u2083 us\u2082","gloss":"planking side","word_count":4},{"line_label":"o 3","line_ref":"P214772.5","transliteration":"3(u@c) la\u2082 1(a\u0161@c) gu\u2082 {ge\u0161}eme","gloss":"less load plow-share","word_count":5},{"line_label":"o 4","line_ref":"P214772.6","transliteration":"1(u@c) ma\u2082-gu\u2082","gloss":"a part of a boat","word_count":2},{"line_label":"o 5","line_ref":"P214772.7","transliteration":"2(u) 5(a\u0161@c) gu\u2082 gi gu-ru\u2081\u2084","gloss":"load reed","word_count":5},{"line_label":"o 6","line_ref":"P214772.8","transliteration":"x-me-la","gloss":"","word_count":1},{"line_label":"o 7","line_ref":"P214772.9","transliteration":"mu-tum\u2082","gloss":"bring","word_count":1},{"line_label":"r 1","line_ref":"P214772.11","transliteration":"x x e\u2082 x","gloss":"house","word_count":4},{"line_label":"r 2","line_ref":"P214772.12","transliteration":"x {ge\u0161}gag","gloss":"nail","word_count":2},{"line_label":"r 3","line_ref":"P214772.13","transliteration":"x x-a ba-de\u2086","gloss":"carry","word_count":3}],"akkadian_words":[]}