{"textid":"P215788","corpus":"admin_oakk","title":"GMII \u2014 = Nik 2, 007","period":"Old Akkadian","genre":"Administrative","subgenre":"","provenience":"Umma","total_lines":5,"total_words":29,"lines":[{"line_label":"o 1","line_ref":"P215788.3","transliteration":"1(ge\u0161\u02beu@c) la\u2082 2(u@c) 6(a\u0161@c) guru\u0161","gloss":"less young adult male","word_count":5},{"line_label":"o 2","line_ref":"P215788.4","transliteration":"2(u@c) 2(a\u0161@c) nar","gloss":"musician","word_count":3},{"line_label":"o 3","line_ref":"P215788.5","transliteration":"erin\u2082 a-ra\u2082 4(u) 3(di\u0161@t)-kam-ma nig\u2082 gu\u2087-a","gloss":"people times thing eat","word_count":6},{"line_label":"o 4","line_ref":"P215788.6","transliteration":"kin ak 1(di\u0161@t) iti 2(u) la\u2082 1(di\u0161@t) u\u2084","gloss":"work do month less sun","word_count":8},{"line_label":"o 5","line_ref":"P215788.7","transliteration":"5(di\u0161@t) mu 3(di\u0161@t) iti 1(u) 2(di\u0161@t) u\u2084","gloss":"year month two sun","word_count":7}],"akkadian_words":[]}