{"textid":"P215340","corpus":"admin_oakk","title":"Ashm 1930-0148 = MAD 5, 013","period":"Old Akkadian","genre":"Administrative","subgenre":"","provenience":"Kish","total_lines":10,"total_words":22,"lines":[{"line_label":"o 1","line_ref":"P215340.3","transliteration":"im\u2086-ta\u2082-lik gu\u2082","gloss":"00","word_count":2},{"line_label":"o 2","line_ref":"P215340.4","transliteration":"ugula mu-tu-tu","gloss":"overseer 00","word_count":2},{"line_label":"o 3","line_ref":"P215340.5","transliteration":"1(a\u0161@c) i\u2083-lu-lu","gloss":"00","word_count":2},{"line_label":"o 4","line_ref":"P215340.6","transliteration":"ugula ip-qum","gloss":"overseer 00","word_count":2},{"line_label":"o 5","line_ref":"P215340.7","transliteration":"1(a\u0161@c) dingir-qar gu\u2082","gloss":"00","word_count":3},{"line_label":"o 6","line_ref":"P215340.8","transliteration":"ugula mar-tu","gloss":"overseer westerner","word_count":2},{"line_label":"o 7","line_ref":"P215340.9","transliteration":"1(a\u0161@c) dingir-gal-zu gu\u2082","gloss":"00","word_count":3},{"line_label":"o 8","line_ref":"P215340.10","transliteration":"1(a\u0161@c) i\u2083-la-ak-nu-id","gloss":"00","word_count":2},{"line_label":"o 9","line_ref":"P215340.11","transliteration":"1(a\u0161@c) i\u2083-la-la","gloss":"0","word_count":2},{"line_label":"o 10","line_ref":"P215340.12","transliteration":"ugula ni-su-dan-nam","gloss":"overseer 00","word_count":2}],"akkadian_words":[]}