{"textid":"P237314","corpus":"saa_astrology","title":"SAA 08 523","period":"Neo-Assyrian","genre":"Astrological Report","subgenre":"lunar","provenience":"Kuyunjik (Nineveh)","total_lines":14,"total_words":60,"lines":[{"line_label":"o 1","line_ref":"P237314.2","transliteration":"1 UD 14-KAM\u2082 30 u 20 KI a-ha-me\u0161","gloss":"day 1 and 1 with one another","word_count":8},{"line_label":"o 2","line_ref":"P237314.3","transliteration":"IGI-ME\u0160 KA GI.NA \u0160A\u2083 KUR DUG\u2083","gloss":"be(come) seen speech reliable mood land be(come) good","word_count":6},{"line_label":"o 3","line_ref":"P237314.4","transliteration":"DINGIR-ME\u0160 KUR-URI{KI} ana SIG\u2085-tim","gloss":"god Akkad for good thing","word_count":4},{"line_label":"o 4","line_ref":"P237314.5","transliteration":"i-ha-sa-su bu-ul KUR-URI{KI}","gloss":"remember cattle Akkad","word_count":3},{"line_label":"o 5","line_ref":"P237314.6","transliteration":"par-ga-ni\u0161 ina EDIN i-rab-bi-i\u1e63","gloss":"undisturbed in open country lie down","word_count":4},{"line_label":"o 6","line_ref":"P237314.7","transliteration":"hu-ud \u0160A\u2083-bi UN-ME\u0160 GAR-an","gloss":"joy heart people be(come) placed","word_count":4},{"line_label":"o 7","line_ref":"P237314.8","transliteration":"\u0160A\u2083-bi LUGAL DUG\u2083-ab","gloss":"mood king be(come) good","word_count":3},{"line_label":"r 1","line_ref":"P237314.10","transliteration":"1 30 u 20 \u0161u-ta-tu-u\u2082","gloss":"1 and 1 being in opposition","word_count":5},{"line_label":"r 2","line_ref":"P237314.11","transliteration":"LUGAL KUR uz-nu u\u2082-rap-pa-a\u0161\u2082","gloss":"king land understanding widen","word_count":4},{"line_label":"r 3","line_ref":"P237314.12","transliteration":"LUGAL SUHU\u0160 {GI\u0160}GU.ZA-\u0161u\u2082 GIN","gloss":"king foundation throne be(come) permanent//be(come) stable","word_count":4},{"line_label":"r 4","line_ref":"P237314.13","transliteration":"1 30 u 20 \u0161it-qul-lu","gloss":"1 and 1 balanced","word_count":5},{"line_label":"r 5","line_ref":"P237314.14","transliteration":"at-mu-u\u2082 ki-i-nu","gloss":"speech reliable","word_count":2},{"line_label":"r 6","line_ref":"P237314.15","transliteration":"ina pi-i UN-ME\u0160 GAR","gloss":"in mouth people be(come) placed","word_count":4},{"line_label":"r 7","line_ref":"P237314.17","transliteration":"\u0161a\u2082 {1}{d}AG-x+x x x","gloss":"from","word_count":4}],"akkadian_words":[{"form":"1","cf":"","gw":"","pos":"","lang":"akk-x-stdbab","line_ref":"P237314.2","position":0},{"form":"UD","cf":"\u016bm","gw":"day","pos":"N","lang":"akk-x-stdbab","line_ref":"P237314.2","position":1},{"form":"14-KAM\u2082","cf":"","gw":"","pos":"","lang":"akk-x-stdbab","line_ref":"P237314.2","position":2},{"form":"30","cf":"Sin","gw":"1","pos":"DN","lang":"akk-x-stdbab","line_ref":"P237314.2","position":3},{"form":"u","cf":"u","gw":"and","pos":"CNJ","lang":"akk-x-stdbab","line_ref":"P237314.2","position":4},{"form":"20","cf":"\u0160ama\u0161","gw":"1","pos":"DN","lang":"akk-x-stdbab","line_ref":"P237314.2","position":5},{"form":"KI","cf":"itti","gw":"with","pos":"PRP","lang":"akk-x-stdbab","line_ref":"P237314.2","position":6},{"form":"a-ha-me\u0161","cf":"ah\u0101me\u0161","gw":"one another","pos":"AV","lang":"akk-x-stdbab","line_ref":"P237314.2","position":7},{"form":"IGI-ME\u0160","cf":"innamr\u016b","gw":"be(come) seen","pos":"V","lang":"akk-x-stdbab","line_ref":"P237314.3","position":0},{"form":"KA","cf":"p\u00fb","gw":"speech","pos":"N","lang":"akk-x-stdbab","line_ref":"P237314.3","position":1},{"form":"GI.NA","cf":"k\u012bnu","gw":"reliable","pos":"AJ","lang":"akk-x-stdbab","line_ref":"P237314.3","position":2},{"form":"\u0160A\u2083","cf":"libbi","gw":"mood","pos":"N","lang":"akk-x-stdbab","line_ref":"P237314.3","position":3},{"form":"KUR","cf":"m\u0101ti","gw":"land","pos":"N","lang":"akk-x-stdbab","line_ref":"P237314.3","position":4},{"form":"DUG\u2083","cf":"i\u1e6d\u00e2b","gw":"be(come) good","pos":"V","lang":"akk-x-stdbab","line_ref":"P237314.3","position":5},{"form":"DINGIR-ME\u0160","cf":"il\u0101ni","gw":"god","pos":"N","lang":"akk-x-stdbab","line_ref":"P237314.4","position":0},{"form":"KUR-URI{KI}","cf":"Mat-Akkadi","gw":"Akkad","pos":"GN","lang":"akk-x-stdbab","line_ref":"P237314.4","position":1},{"form":"ana","cf":"ana","gw":"for","pos":"PRP","lang":"akk-x-stdbab","line_ref":"P237314.4","position":2},{"form":"SIG\u2085-tim","cf":"damiqti","gw":"good thing","pos":"'N","lang":"akk-x-stdbab","line_ref":"P237314.4","position":3},{"form":"i-ha-sa-su","cf":"ihassas\u016b","gw":"remember","pos":"V","lang":"akk-x-stdbab","line_ref":"P237314.5","position":0},{"form":"bu-ul","cf":"b\u016bl","gw":"cattle","pos":"N","lang":"akk-x-stdbab","line_ref":"P237314.5","position":1},{"form":"KUR-URI{KI}","cf":"Mat-Akkadi","gw":"Akkad","pos":"GN","lang":"akk-x-stdbab","line_ref":"P237314.5","position":2},{"form":"par-ga-ni\u0161","cf":"parg\u0101ni\u0161","gw":"undisturbed","pos":"AV","lang":"akk-x-stdbab","line_ref":"P237314.6","position":0},{"form":"ina","cf":"ina","gw":"in","pos":"PRP","lang":"akk-x-stdbab","line_ref":"P237314.6","position":1},{"form":"EDIN","cf":"\u1e63\u0113ri","gw":"open country","pos":"N","lang":"akk-x-stdbab","line_ref":"P237314.6","position":2},{"form":"i-rab-bi-i\u1e63","cf":"irabbi\u1e63","gw":"lie down","pos":"V","lang":"akk-x-stdbab","line_ref":"P237314.6","position":3},{"form":"hu-ud","cf":"h\u016bd","gw":"joy","pos":"N","lang":"akk-x-stdbab","line_ref":"P237314.7","position":0},{"form":"\u0160A\u2083-bi","cf":"libbi","gw":"heart","pos":"N","lang":"akk-x-stdbab","line_ref":"P237314.7","position":1},{"form":"UN-ME\u0160","cf":"ni\u0161\u0113","gw":"people","pos":"N","lang":"akk-x-stdbab","line_ref":"P237314.7","position":2},{"form":"GAR-an","cf":"i\u0161\u0161akkan","gw":"be(come) placed","pos":"V","lang":"akk-x-stdbab","line_ref":"P237314.7","position":3},{"form":"\u0160A\u2083-bi","cf":"libbi","gw":"mood","pos":"N","lang":"akk-x-stdbab","line_ref":"P237314.8","position":0},{"form":"LUGAL","cf":"\u0161arri","gw":"king","pos":"N","lang":"akk-x-stdbab","line_ref":"P237314.8","position":1},{"form":"DUG\u2083-ab","cf":"i\u1e6d\u00e2b","gw":"be(come) good","pos":"V","lang":"akk-x-stdbab","line_ref":"P237314.8","position":2},{"form":"1","cf":"","gw":"","pos":"","lang":"akk-x-stdbab","line_ref":"P237314.10","position":0},{"form":"30","cf":"Sin","gw":"1","pos":"DN","lang":"akk-x-stdbab","line_ref":"P237314.10","position":1},{"form":"u","cf":"u","gw":"and","pos":"CNJ","lang":"akk-x-stdbab","line_ref":"P237314.10","position":2},{"form":"20","cf":"\u0160ama\u0161","gw":"1","pos":"DN","lang":"akk-x-stdbab","line_ref":"P237314.10","position":3},{"form":"\u0161u-ta-tu-u\u2082","cf":"\u0161ut\u0101t\u00fb","gw":"being in opposition","pos":"AJ","lang":"akk-x-stdbab","line_ref":"P237314.10","position":4},{"form":"LUGAL","cf":"\u0161ar","gw":"king","pos":"N","lang":"akk-x-stdbab","line_ref":"P237314.11","position":0},{"form":"KUR","cf":"m\u0101ti","gw":"land","pos":"N","lang":"akk-x-stdbab","line_ref":"P237314.11","position":1},{"form":"uz-nu","cf":"uznu","gw":"understanding","pos":"N","lang":"akk-x-stdbab","line_ref":"P237314.11","position":2},{"form":"u\u2082-rap-pa-a\u0161\u2082","cf":"urappa\u0161","gw":"widen","pos":"V","lang":"akk-x-stdbab","line_ref":"P237314.11","position":3},{"form":"LUGAL","cf":"\u0161ar","gw":"king","pos":"N","lang":"akk-x-stdbab","line_ref":"P237314.12","position":0},{"form":"SUHU\u0160","cf":"i\u0161id","gw":"foundation","pos":"N","lang":"akk-x-stdbab","line_ref":"P237314.12","position":1},{"form":"{GI\u0160}GU.ZA-\u0161u\u2082","cf":"kuss\u00ee\u0161u","gw":"throne","pos":"N","lang":"akk-x-stdbab","line_ref":"P237314.12","position":2},{"form":"GIN","cf":"k\u00e2nu","gw":"be(come) permanent//be(come) stable","pos":"V'V$ik\u00e2n","lang":"akk-x-stdbab","line_ref":"P237314.12","position":3},{"form":"1","cf":"","gw":"","pos":"","lang":"akk-x-stdbab","line_ref":"P237314.13","position":0},{"form":"30","cf":"Sin","gw":"1","pos":"DN","lang":"akk-x-stdbab","line_ref":"P237314.13","position":1},{"form":"u","cf":"u","gw":"and","pos":"CNJ","lang":"akk-x-stdbab","line_ref":"P237314.13","position":2},{"form":"20","cf":"\u0160ama\u0161","gw":"1","pos":"DN","lang":"akk-x-stdbab","line_ref":"P237314.13","position":3},{"form":"\u0161it-qul-lu","cf":"\u0161itqul\u016b","gw":"balanced","pos":"AJ","lang":"akk-x-stdbab","line_ref":"P237314.13","position":4},{"form":"at-mu-u\u2082","cf":"atm\u00fb","gw":"speech","pos":"N","lang":"akk-x-stdbab","line_ref":"P237314.14","position":0},{"form":"ki-i-nu","cf":"k\u012bnu","gw":"reliable","pos":"AJ","lang":"akk-x-stdbab","line_ref":"P237314.14","position":1},{"form":"ina","cf":"ina","gw":"in","pos":"PRP","lang":"akk-x-stdbab","line_ref":"P237314.15","position":0},{"form":"pi-i","cf":"p\u00ee","gw":"mouth","pos":"N","lang":"akk-x-stdbab","line_ref":"P237314.15","position":1},{"form":"UN-ME\u0160","cf":"ni\u0161\u0113","gw":"people","pos":"N","lang":"akk-x-stdbab","line_ref":"P237314.15","position":2},{"form":"GAR","cf":"i\u0161\u0161akkan","gw":"be(come) placed","pos":"V","lang":"akk-x-stdbab","line_ref":"P237314.15","position":3},{"form":"\u0161a\u2082","cf":"\u0161a","gw":"from","pos":"'PRP","lang":"akk-x-neobab","line_ref":"P237314.17","position":0},{"form":"{1}{d}AG-x+x","cf":"","gw":"","pos":"","lang":"akk-x-neobab","line_ref":"P237314.17","position":1},{"form":"x","cf":"","gw":"","pos":"","lang":"akk-x-neobab","line_ref":"P237314.17","position":2},{"form":"x","cf":"","gw":"","pos":"","lang":"akk-x-neobab","line_ref":"P237314.17","position":3}]}