{"textid":"P323199","corpus":"admin_oakk","title":"CUNES 48-12-085 = CUSAS 19, 123","period":"Old Akkadian","genre":"Administrative","subgenre":"","provenience":"Adab","total_lines":10,"total_words":20,"lines":[{"line_label":"o 1","line_ref":"P323199.3","transliteration":"n 3(ban\u2082@c) zi\u2083-gu","gloss":"a type of flour","word_count":3},{"line_label":"o 2","line_ref":"P323199.4","transliteration":"2(a\u0161@c) ku\u0161 a-ga\u2082-la\u2082","gloss":"skin sack","word_count":3},{"line_label":"o 3","line_ref":"P323199.5","transliteration":"an-si","gloss":"fill","word_count":1},{"line_label":"o 4","line_ref":"P323199.6","transliteration":"n 1(ban\u2082@c) zi\u2083 za-tum","gloss":"flour a flour","word_count":4},{"line_label":"o 5","line_ref":"P323199.7","transliteration":"x HA-um","gloss":"","word_count":2},{"line_label":"r 1","line_ref":"P323199.9","transliteration":"n ku\u0161 a-ga\u2082-la\u2082","gloss":"skin sack","word_count":3},{"line_label":"r 2","line_ref":"P323199.10","transliteration":"an-si","gloss":"fill","word_count":1},{"line_label":"r 3","line_ref":"P323199.11","transliteration":"gu\u2082-du\u2088-a{ki}","gloss":"1","word_count":1},{"line_label":"r 4","line_ref":"P323199.12","transliteration":"nam-ti-e\u2082-mah-ta","gloss":"00","word_count":1},{"line_label":"r 5","line_ref":"P323199.13","transliteration":"an-na-\u0161um\u2082","gloss":"give","word_count":1}],"akkadian_words":[]}