{"textid":"P369028","corpus":"babylonian_literary","title":"KAR 046 (VAT 09773)","period":"Neo-Assyrian","genre":"Prayer/Incantation","subgenre":"Incantation against the Oath","provenience":"Assur","total_lines":27,"total_words":106,"lines":[{"line_label":"o 1","line_ref":"P369028.3","transliteration":"ab-ta \u0161a\u2082 ina ap-ti u\u2082-\u0161a\u2082-ru ugu ba-da-la\u2082-e","gloss":"window that in window bend down//lean forward skull hang","word_count":7},{"line_label":"o 2","line_ref":"P369028.5","transliteration":"gu\u2082-bi he\u2082-ni-ib\u2082-\u0161um-mu-ne","gloss":"neck slaughter","word_count":2},{"line_label":"","line_ref":"","transliteration":"ab ti-ta igi x-ne","gloss":"window side eye","word_count":4},{"line_label":"","line_ref":"","transliteration":"\u0161a\u2082 ina ap-ti \u1e63e-li ip-pal-x","gloss":"who in window side","word_count":5},{"line_label":"o 4","line_ref":"P369028.9","transliteration":"igi-bi pa-ni-\u0161u lim-hu-\u1e63u he\u2082-en-sag\u2083-e-ne","gloss":"face front//face beat strike","word_count":4},{"line_label":"","line_ref":"","transliteration":"ab igi la\u2082-ta gu\u2083 mu-un-na-an-de\u2082-e","gloss":"window eye hang voice pour","word_count":5},{"line_label":"","line_ref":"","transliteration":"\u0161a\u2082 ina ap-ti mu-\u0161er\u2082-ti i-\u0161es-sa-a","gloss":"that in window overlooking window shout","word_count":5},{"line_label":"o 6","line_ref":"P369028.13","transliteration":"ka-bi pa-a-\u0161u\u2082 li-de-lu-\u0161u\u2082 he\u2082-en-tab-e-ne","gloss":"mouth mouth shut block","word_count":4},{"line_label":"","line_ref":"","transliteration":"ab sa\u014b-ga-ta mu-un-da-ab-\u0161u\u2082-\u0161u\u2082-e-ne","gloss":"window head envelop","word_count":3},{"line_label":"","line_ref":"","transliteration":"\u0161a\u2082 ina ap-ti mu-hi it-ta-na-sa-ha-pu","gloss":"that in window skull//top envelop//overwhelm","word_count":5},{"line_label":"","line_ref":"","transliteration":"gakkul nu-bad-da-ta he\u2082-ni-ib\u2082-\u0161u\u2082-\u0161u\u2082-e-ne","gloss":"mash-tub open cover","word_count":3},{"line_label":"","line_ref":"","transliteration":"x","gloss":"","word_count":1},{"line_label":"","line_ref":"","transliteration":"x","gloss":"","word_count":1},{"line_label":"","line_ref":"","transliteration":"\u0161a\u2082 ina na-ma-ri i-te-ne\u2082-ek-ke-lu","gloss":"that in be(come) bright//be(com)ing bright be(come) dark//repeatedly become dark","word_count":4},{"line_label":"","line_ref":"","transliteration":"zalag\u2082-ta ki {d}utu e\u2083 he\u2082-ni-ib\u2082-zi-zi-e-ne","gloss":"bright place 1 leave cut","word_count":5},{"line_label":"","line_ref":"","transliteration":"ina na-ma-ri a-\u0161ar \u1e63i-it {d}UTU{+\u0161i} li-is-su-hu-\u0161u","gloss":"in be(come) bright//be(com)ing bright place exit sun tear out","word_count":6},{"line_label":"","line_ref":"","transliteration":"ku\u2081\u2080-ku\u2081\u2080 nim-\u014bir\u2082-gin\u2087 mu-un-\u014bir\u2082-\u014bir\u2082-re-e-ne","gloss":"dark places lightning bolt flash","word_count":3},{"line_label":"","line_ref":"","transliteration":"\u0161a\u2082 ina ek-le-ti GIM bir-qi\u2082 it-ta-nab-ri-qu","gloss":"that in darkness like lightning (flash) lighten//flash","word_count":6},{"line_label":"","line_ref":"","transliteration":"ku\u2081\u2080-ku\u2081\u2080-ga \u0161ag\u2084 irigal-ta he\u2082-ni-ib\u2082-sir\u2083-re-e-ne","gloss":"dark places in grave bind","word_count":4},{"line_label":"","line_ref":"","transliteration":"ina ek-le-ti ina qe\u2082-reb qab-li li-ik-lu-\u0161u","gloss":"in darkness in inside grave hold (back)","word_count":6},{"line_label":"","line_ref":"","transliteration":"pu\u2082-ta mu-un-\u0161i-ni-ib\u2082-ed\u2083-de\u2083","gloss":"cistern go up","word_count":2},{"line_label":"","line_ref":"","transliteration":"\u0161a\u2082 ul-tu bur-ti il-la-a","gloss":"that from cistern//well rise","word_count":4},{"line_label":"","line_ref":"","transliteration":"ub\u2084 ni\u014b\u2082-hu\u0161-a-ta he\u2082-ni-ib\u2082-\u0161ub-bu-ne","gloss":"cavity pitfall throw","word_count":3},{"line_label":"","line_ref":"","transliteration":"a-na \u0161u-ut-ta-ti lid-da-\u0161u","gloss":"to (hunter's) pitfall throw","word_count":3},{"line_label":"","line_ref":"","transliteration":"pu\u2082 du\u2081\u2080-us\u2082-sa-ta mu-un-da-an-gir\u2085-e-ne","gloss":"cistern bathroom slip (in or through)","word_count":3},{"line_label":"","line_ref":"","transliteration":"\u0161a\u2082 ina bur-ti nar\u2083-ma-ki i-hal-lu-pa\u2082","gloss":"that in cistern//well (cultic) washing//bath slip into","word_count":5},{"line_label":"r 7","line_ref":"P369028.33","transliteration":"ana ne-pe-\u0161u\u2082 ZI{+ha}","gloss":"for activity//ritual torn out//excerpted","word_count":3}],"akkadian_words":[{"form":"\u0161a\u2082","cf":"\u0161a","gw":"that","pos":"REL","lang":"akk-x-stdbab","line_ref":"P369028.3","position":1},{"form":"ina","cf":"ina","gw":"in","pos":"PRP","lang":"akk-x-stdbab","line_ref":"P369028.3","position":2},{"form":"ap-ti","cf":"apti","gw":"window","pos":"N","lang":"akk-x-stdbab","line_ref":"P369028.3","position":3},{"form":"u\u2082-\u0161a\u2082-ru","cf":"\u0161urru","gw":"bend down//lean forward","pos":"V'V$u\u0161arru","lang":"akk-x-stdbab","line_ref":"P369028.3","position":4},{"form":"\u0161a\u2082","cf":"\u0161a","gw":"who","pos":"REL","lang":"akk-x-stdbab","line_ref":"","position":0},{"form":"ina","cf":"ina","gw":"in","pos":"PRP","lang":"akk-x-stdbab","line_ref":"","position":1},{"form":"ap-ti","cf":"apti","gw":"window","pos":"N","lang":"akk-x-stdbab","line_ref":"","position":2},{"form":"\u1e63e-li","cf":"\u1e63\u0113li","gw":"side","pos":"N","lang":"akk-x-stdbab","line_ref":"","position":3},{"form":"ip-pal-x","cf":"","gw":"","pos":"","lang":"akk-x-stdbab","line_ref":"","position":4},{"form":"pa-ni-\u0161u","cf":"p\u0101nu","gw":"front//face","pos":"N'N$p\u0101n\u012b\u0161u","lang":"akk-x-stdbab","line_ref":"P369028.9","position":1},{"form":"lim-hu-\u1e63u","cf":"mah\u0101\u1e63u","gw":"beat","pos":"V$limhu\u1e63\u016b","lang":"akk-x-stdbab","line_ref":"P369028.9","position":2},{"form":"\u0161a\u2082","cf":"\u0161a","gw":"that","pos":"REL","lang":"akk-x-stdbab","line_ref":"","position":0},{"form":"ina","cf":"ina","gw":"in","pos":"PRP","lang":"akk-x-stdbab","line_ref":"","position":1},{"form":"ap-ti","cf":"apti","gw":"window","pos":"N","lang":"akk-x-stdbab","line_ref":"","position":2},{"form":"mu-\u0161er\u2082-ti","cf":"mu\u0161\u0113rtu","gw":"overlooking window","pos":"N$mu\u0161\u0113rti","lang":"akk-x-stdbab","line_ref":"","position":3},{"form":"i-\u0161es-sa-a","cf":"\u0161as\u00fb","gw":"shout","pos":"V$i\u0161ess\u00e2","lang":"akk-x-stdbab","line_ref":"","position":4},{"form":"pa-a-\u0161u\u2082","cf":"p\u00fb","gw":"mouth","pos":"N$p\u00e2\u0161u","lang":"akk-x-stdbab","line_ref":"P369028.13","position":1},{"form":"li-de-lu-\u0161u\u2082","cf":"ed\u0113lu","gw":"shut","pos":"V$l\u012bdel\u016b\u0161u","lang":"akk-x-stdbab","line_ref":"P369028.13","position":2},{"form":"\u0161a\u2082","cf":"\u0161a","gw":"that","pos":"REL","lang":"akk-x-stdbab","line_ref":"","position":0},{"form":"ina","cf":"ina","gw":"in","pos":"PRP","lang":"akk-x-stdbab","line_ref":"","position":1},{"form":"ap-ti","cf":"apti","gw":"window","pos":"N","lang":"akk-x-stdbab","line_ref":"","position":2},{"form":"mu-hi","cf":"muhhu","gw":"skull//top","pos":"N'N$muhhi","lang":"akk-x-stdbab","line_ref":"","position":3},{"form":"it-ta-na-sa-ha-pu","cf":"sah\u0101pu","gw":"envelop//overwhelm","pos":"V'V$ittanasahapu","lang":"akk-x-stdbab","line_ref":"","position":4},{"form":"x","cf":"","gw":"","pos":"","lang":"akk-x-stdbab","line_ref":"","position":0},{"form":"\u0161a\u2082","cf":"\u0161a","gw":"that","pos":"REL","lang":"akk-x-stdbab","line_ref":"","position":0},{"form":"ina","cf":"ina","gw":"in","pos":"PRP","lang":"akk-x-stdbab","line_ref":"","position":1},{"form":"na-ma-ri","cf":"naw\u0101ru","gw":"be(come) bright//be(com)ing bright","pos":"V'N$nam\u0101ri","lang":"akk-x-stdbab","line_ref":"","position":2},{"form":"i-te-ne\u2082-ek-ke-lu","cf":"ek\u0113lu","gw":"be(come) dark//repeatedly become dark","pos":"V'V$\u012btenekkelu","lang":"akk-x-stdbab","line_ref":"","position":3},{"form":"ina","cf":"ina","gw":"in","pos":"PRP","lang":"akk-x-stdbab","line_ref":"","position":0},{"form":"na-ma-ri","cf":"naw\u0101ru","gw":"be(come) bright//be(com)ing bright","pos":"V'N$nam\u0101ri","lang":"akk-x-stdbab","line_ref":"","position":1},{"form":"a-\u0161ar","cf":"a\u0161ar","gw":"place","pos":"N","lang":"akk-x-stdbab","line_ref":"","position":2},{"form":"\u1e63i-it","cf":"\u1e63\u012bt","gw":"exit","pos":"N","lang":"akk-x-stdbab","line_ref":"","position":3},{"form":"{d}UTU{+\u0161i}","cf":"\u0161am\u0161i","gw":"sun","pos":"N","lang":"akk-x-stdbab","line_ref":"","position":4},{"form":"li-is-su-hu-\u0161u","cf":"nas\u0101hu","gw":"tear out","pos":"V$lissuh\u016b\u0161u","lang":"akk-x-stdbab","line_ref":"","position":5},{"form":"\u0161a\u2082","cf":"\u0161a","gw":"that","pos":"REL","lang":"akk-x-stdbab","line_ref":"","position":0},{"form":"ina","cf":"ina","gw":"in","pos":"PRP","lang":"akk-x-stdbab","line_ref":"","position":1},{"form":"ek-le-ti","cf":"ekleti","gw":"darkness","pos":"N","lang":"akk-x-stdbab","line_ref":"","position":2},{"form":"GIM","cf":"k\u012bma","gw":"like","pos":"PRP","lang":"akk-x-stdbab","line_ref":"","position":3},{"form":"bir-qi\u2082","cf":"birqi","gw":"lightning (flash)","pos":"N","lang":"akk-x-stdbab","line_ref":"","position":4},{"form":"it-ta-nab-ri-qu","cf":"bar\u0101qu","gw":"lighten//flash","pos":"V'V$ittanabriqu","lang":"akk-x-stdbab","line_ref":"","position":5},{"form":"ina","cf":"ina","gw":"in","pos":"PRP","lang":"akk-x-stdbab","line_ref":"","position":0},{"form":"ek-le-ti","cf":"ekleti","gw":"darkness","pos":"N","lang":"akk-x-stdbab","line_ref":"","position":1},{"form":"ina","cf":"ina","gw":"in","pos":"PRP","lang":"akk-x-stdbab","line_ref":"","position":2},{"form":"qe\u2082-reb","cf":"qereb","gw":"inside","pos":"N","lang":"akk-x-stdbab","line_ref":"","position":3},{"form":"qab-li","cf":"qabru","gw":"grave","pos":"N$qabli","lang":"akk-x-stdbab","line_ref":"","position":4},{"form":"li-ik-lu-\u0161u","cf":"kal\u00fb","gw":"hold (back)","pos":"V$likl\u00fb\u0161u","lang":"akk-x-stdbab","line_ref":"","position":5},{"form":"\u0161a\u2082","cf":"\u0161a","gw":"that","pos":"REL","lang":"akk-x-stdbab","line_ref":"","position":0},{"form":"ul-tu","cf":"ultu","gw":"from","pos":"PRP","lang":"akk-x-stdbab","line_ref":"","position":1},{"form":"bur-ti","cf":"b\u016brtu","gw":"cistern//well","pos":"N'N$b\u016brti","lang":"akk-x-stdbab","line_ref":"","position":2},{"form":"il-la-a","cf":"ill\u00e2","gw":"rise","pos":"V","lang":"akk-x-stdbab","line_ref":"","position":3},{"form":"a-na","cf":"ana","gw":"to","pos":"PRP","lang":"akk-x-stdbab","line_ref":"","position":0},{"form":"\u0161u-ut-ta-ti","cf":"\u0161uttatu","gw":"(hunter's) pitfall","pos":"N$\u0161uttati","lang":"akk-x-stdbab","line_ref":"","position":1},{"form":"lid-da-\u0161u","cf":"nad\u00fb","gw":"throw","pos":"V$lidd\u00e2\u0161u","lang":"akk-x-stdbab","line_ref":"","position":2},{"form":"\u0161a\u2082","cf":"\u0161a","gw":"that","pos":"REL","lang":"akk-x-stdbab","line_ref":"","position":0},{"form":"ina","cf":"ina","gw":"in","pos":"PRP","lang":"akk-x-stdbab","line_ref":"","position":1},{"form":"bur-ti","cf":"b\u016brtu","gw":"cistern//well","pos":"N'N$b\u016brti","lang":"akk-x-stdbab","line_ref":"","position":2},{"form":"nar\u2083-ma-ki","cf":"narmaku","gw":"(cultic) washing//bath","pos":"N'N$narmaki","lang":"akk-x-stdbab","line_ref":"","position":3},{"form":"i-hal-lu-pa\u2082","cf":"hal\u0101pu","gw":"slip into","pos":"V$ihallupa","lang":"akk-x-stdbab","line_ref":"","position":4},{"form":"ana","cf":"ana","gw":"for","pos":"PRP","lang":"akk-x-stdbab","line_ref":"P369028.33","position":0},{"form":"ne-pe-\u0161u\u2082","cf":"n\u0113pe\u0161u","gw":"activity//ritual","pos":"N$","lang":"akk-x-stdbab","line_ref":"P369028.33","position":1},{"form":"ZI{+ha}","cf":"nashu","gw":"torn out//excerpted","pos":"AJ'AJ$nasha","lang":"akk-x-stdbab","line_ref":"P369028.33","position":2}]}