{"textid":"Q003448","corpus":"rinap_tiglath_pileser","title":"Tiglath-pileser III 35","period":"Neo-Assyrian","genre":"Royal Inscription","subgenre":"Tiglath-pileser III","provenience":"Luristan","total_lines":171,"total_words":935,"lines":[{"line_label":"i 1","line_ref":"Q003448.3","transliteration":"a\u0161-\u0161ur EN GAL {d}EN.LIL\u2082.LA\u2082 DINGIR.ME\u0160 mu-\u0161i-me NAM.ME\u0160","gloss":"1 lord great 1 god one who determines fate","word_count":7},{"line_label":"i 2","line_ref":"Q003448.4","transliteration":"{d}AMAR.UTU mu\u0161-te-\u0161ir GI\u0160.HUR DU\u2083-ni-u mit-hur-ti pa-qid","gloss":"1 one who sets straight drawing//plan creator convergence//harmony carer","word_count":6},{"line_label":"i 3","line_ref":"Q003448.5","transliteration":"x mu-u\u2082-kin i\u0161-di KUR","gloss":"witness//one who firmly establishes foundation land","word_count":4},{"line_label":"i 4","line_ref":"Q003448.6","transliteration":"{d}AG ta-mi-ih GI.DUB na-\u0161i DUB \u0161i-mat DINGIR.DINGIR","gloss":"1 one who grasps stylus bearer tablet what is fixed//fate god","word_count":7},{"line_label":"i 5","line_ref":"Q003448.7","transliteration":"x {d}U.GUR GIR\u2083.GIR\u2083.GIR\u2083","gloss":"1","word_count":3},{"line_label":"i 6","line_ref":"Q003448.8","transliteration":"x \u0161a\u2082 la IGI-ru qa-bal-\u0161u\u2082","gloss":"who not face//be faced battle","word_count":5},{"line_label":"i 7","line_ref":"Q003448.9","transliteration":"{d}UTU \u0161a-ki-ni GI\u0160.MI x x x ME\u0160","gloss":"1 one who places shade//protection","word_count":7},{"line_label":"i 8","line_ref":"Q003448.10","transliteration":"{d}30 na-an-na-ru nam-ru na-din {GI\u0160}GIDRU AGA mu-kin be-lu-ti","gloss":"1 light of the sky bright giver sceptre crown one who firmly establishes rule//lordship","word_count":8},{"line_label":"i 9","line_ref":"Q003448.11","transliteration":"{d}I\u0160KUR GU\u2082.GAL AN-e KI-tim mu-kam\u2082-mir \u1e6duh-di HE\u2082.GAL\u2082 x x","gloss":"1 irrigation controller heaven earth one who heaps up abundance plenty","word_count":9},{"line_label":"i 10","line_ref":"Q003448.12","transliteration":"{d}e\u2082-a EN ne\u2082-me-qi pa-tiq kul-lat mim-ma \u0161um-\u0161u\u2082 mu-ban-ni-u nab-ni-ti","gloss":"1 lord wisdom one who fashions all of anything name one who beautifies//one who treats well creatures","word_count":9},{"line_label":"i 11","line_ref":"Q003448.13","transliteration":"{d}15 x ra-i-mat LUGAL \u0160E.GA-\u0161a\u2082 mu-x-x x-ti","gloss":"1 one who loves king consent//favourite","word_count":7},{"line_label":"i 12","line_ref":"Q003448.14","transliteration":"{d}7.BI EN.ME\u0160 ge\u0161-ru-ti a-li-kut pa-an ERIM.HI-ia \u0160UB x x x x x x","gloss":"1 lord very strong goer front military force//troops one who who overthrows","word_count":13},{"line_label":"i 13","line_ref":"Q003448.15","transliteration":"{d}MAR.TU x x x x x x x","gloss":"1","word_count":8},{"line_label":"i 14","line_ref":"Q003448.16","transliteration":"x x x","gloss":"","word_count":3},{"line_label":"i 15","line_ref":"Q003448.17","transliteration":"DINGIR.ME\u0160 GAL.ME\u0160 a-\u0161i-bu-tu AN-e KI-tim","gloss":"god great inhabitant heaven netherworld","word_count":5},{"line_label":"i 16","line_ref":"Q003448.18","transliteration":"x x x","gloss":"","word_count":3},{"line_label":"i 17","line_ref":"Q003448.19","transliteration":"x \u0161e mu","gloss":"","word_count":3},{"line_label":"i 18","line_ref":"Q003448.20","transliteration":"x","gloss":"","word_count":1},{"line_label":"i 19","line_ref":"Q003448.21","transliteration":"x","gloss":"","word_count":1},{"line_label":"i 20","line_ref":"Q003448.22","transliteration":"x","gloss":"","word_count":1},{"line_label":"i 21","line_ref":"Q003448.23","transliteration":"{m}tukul-ti-A-e\u2082-\u0161ar\u2082-ra GAR {d}BAD NUN SANGA a\u0161-\u0161ur","gloss":"Tiglath-pileser III, king of Assyria appointee 1 ruler priest 1","word_count":6},{"line_label":"i 22","line_ref":"Q003448.24","transliteration":"x mu-u\u0161-te-e\u02be-u a\u0161\u2082-ri-ku-nu ENSI\u2082","gloss":"repeatedly searching//assiduous one place//(divine) abode vice-regent (of a god)","word_count":4},{"line_label":"i 23","line_ref":"Q003448.25","transliteration":"x x NUNUZ {URU}bal-til \u0161u-qu-ru","gloss":"offspring A\u0161\u0161ur very valuable","word_count":5},{"line_label":"i 24","line_ref":"Q003448.26","transliteration":"x bi-bil\u2082 lib\u2083-bi {d}A.EDIN GA\u0160AN GAL-ti","gloss":"(action of) bringing//desire interior 1 lady great","word_count":6},{"line_label":"i 25","line_ref":"Q003448.27","transliteration":"x x x SUM ARHU\u0160 TUK-\u0161u\u2082 NAM.TI.LA","gloss":"womb//compassion obtain//have life","word_count":7},{"line_label":"i 26","line_ref":"Q003448.28","transliteration":"x MAN ki\u0161-\u0161a\u2082-ti MAN KUR a\u0161-\u0161ur{KI} MAN KUR \u0161u-miri","gloss":"king world king land Assyria king land Sumer","word_count":9},{"line_label":"i 27","line_ref":"Q003448.29","transliteration":"u URI{KI} MAN kib-rat LIMMU\u2082 SIPA ba-\u02beu-la-a-tim","gloss":"and 1 king quarter four shepherd people","word_count":7},{"line_label":"i 28","line_ref":"Q003448.30","transliteration":"GAR an-du-ra-ar KUR a\u0161-\u0161ur mu-\u1e6dib lib\u2083-bi i\u0161\u2088-tar\u2082","gloss":"one who places freedom//exemption land Assyria one who pleases heart","word_count":7},{"line_label":"i 29","line_ref":"Q003448.31","transliteration":"mu-rap-pi\u0161 mi-\u1e63ir KUR a\u0161-\u0161ur","gloss":"one who makes wide border land Assyria","word_count":4},{"line_label":"i 30","line_ref":"Q003448.32","transliteration":"ma-hir GUN u IGI.SA\u2082-e \u0161a\u2082 DU\u2083-\u0161i-na ad-na-ti","gloss":"opponent//recipient tribute and gift of all people","word_count":7},{"line_label":"i 31","line_ref":"Q003448.33","transliteration":"x a-na ru-pu-\u0161i UN.ME\u0160-\u0161a\u2082 DAGAL.ME\u0160","gloss":"to be(come) wide//expanding people wide","word_count":5},{"line_label":"i 32","line_ref":"Q003448.34","transliteration":"x a-bur-ri\u0161 a-na re-\u02bee-e","gloss":"in a green pasture to pasture//shepherding","word_count":4},{"line_label":"i 33","line_ref":"Q003448.35","transliteration":"x i\u0161-ku-un-\u0161u\u2082","gloss":"put//place","word_count":2},{"line_label":"i 34","line_ref":"Q003448.36","transliteration":"x a\u0161-\u0161ur {d}EN.LIL\u2082.LA\u2082","gloss":"1 1","word_count":3},{"line_label":"i 35","line_ref":"Q003448.37","transliteration":"DINGIR.ME\u0160 x-du-u a-na \u0161um-qut la ma-giri u\u2082-\u0161a\u2082-x-x","gloss":"god to cutting down not submissive one","word_count":7},{"line_label":"i 36","line_ref":"Q003448.38","transliteration":"ina SAG LUGAL-ti-ia ina mah-re-e BALA-ia\u2082 ina 6 ITI \u0161a\u2082 ina {GI\u0160}GU.ZA","gloss":"at head//beginning kingship during first reign (of a king)//regnal year during month that on throne","word_count":12},{"line_label":"i 37","line_ref":"Q003448.39","transliteration":"LUGAL-ti ra-bi\u0161 u\u2082-\u0161i-bu ERIM.HI.A-at KUR a\u0161-\u0161ur{KI} gap-\u0161a\u2082-a-ti","gloss":"kingship magnificently sit military force//troops land Assyria arisen","word_count":7},{"line_label":"i 38","line_ref":"Q003448.40","transliteration":"lu ad-ke x","gloss":"may raise//muster","word_count":3},{"line_label":"i 1'","line_ref":"Q003448.42","transliteration":"x U\u2082 x KUR","gloss":"","word_count":4},{"line_label":"i 2'","line_ref":"Q003448.43","transliteration":"x pa-a 1-en","gloss":"mouth one","word_count":3},{"line_label":"i 3'","line_ref":"Q003448.44","transliteration":"u\u2082-\u0161a\u2082-a\u0161\u2082-kin\u2082-\u0161u-nu-ti a-na KUR a\u0161-\u0161ur u\u2082-ra-a\u0161\u2082-\u0161u\u2082-nu-ti","gloss":"put//have established to land Assyria lead","word_count":5},{"line_label":"i 4'","line_ref":"Q003448.45","transliteration":"x {LU\u2082}\u0161u-ut SAG-ia ina UGU-\u0161u\u2082-nu GAR-un","gloss":"who(m) head on skull put//place","word_count":6},{"line_label":"i 5'","line_ref":"Q003448.46","transliteration":"ina 2 BALA-ia ana {KUR}ZALAG\u2082 {KUR}E\u2082-si-in-gi-bu-ti lu al-lik","gloss":"during regnal year to may go","word_count":8},{"line_label":"i 6'","line_ref":"Q003448.47","transliteration":"x {KUR}E\u2082-{m}bar-ru-a","gloss":"1","word_count":2},{"line_label":"i 7'","line_ref":"Q003448.48","transliteration":"x x qu \u0161a\u2082 x MAL x x x x E\u0160 x-ti-ia\u2082","gloss":"of","word_count":12},{"line_label":"i 8'","line_ref":"Q003448.49","transliteration":"x BA-\u0161a\u2082-ni ina {GI\u0160}TUKUL u\u2082-\u0161am-qit \u0161al-la-su-nu","gloss":"give with weapon fall down//cut down booty","word_count":6},{"line_label":"i 9'","line_ref":"Q003448.50","transliteration":"a\u0161\u2082-lu-la {LU\u2082}\u0161u-ut SAG-ia ina UGU {KUR}par-su-a","gloss":"carry off who(m) head on skull","word_count":6},{"line_label":"i 10'","line_ref":"Q003448.51","transliteration":"{LU\u2082}\u0161u-ut SAG-ia\u2082 ina UGU {KUR}E\u2082-ha-am-ban GAR-un KUR.KUR \u0161u-a-ti-na","gloss":"who(m) head on skull 1 put//place land those","word_count":8},{"line_label":"i 11'","line_ref":"Q003448.52","transliteration":"a-na BULUG-ki KUR a\u0161-\u0161ur GUR-er ma-da-tu\u2082 \u0161a\u2082 {m}dal-ta-a {KUR}e-lip\u2082-a-a","gloss":"to boundary marker//boundary land Assyria turn//return payment of king of Ellipi of Ellipi","word_count":9},{"line_label":"i 12'","line_ref":"Q003448.53","transliteration":"{LU\u2082}EN.URU.ME\u0160 {LU\u2082}EN.URU.ME\u0160 \u0161a\u2082 {KUR}ZALAG\u2082 {KUR}sin-gi-bu-te mada-a-a \u0161a\u2082 KUR-e DU\u2083-\u0161u\u2082-nu","gloss":"lord lord of Median of mountain all","word_count":9},{"line_label":"i 13'","line_ref":"Q003448.54","transliteration":"\u0161a\u2082 KUR \u0161am-\u0161i AN\u0160E.KUR.RA.ME\u0160 {AN\u0160E}pa-re-e LAL-at {GI\u0160}ni-ri","gloss":"of rising sun horse mule binding//(yoke-)team yoke","word_count":7},{"line_label":"i 14'","line_ref":"Q003448.55","transliteration":"{AN\u0160E}ud-ra-te GU\u2084.ME\u0160 u \u1e63e-e-ni a-na la mi\u2083-ni am-hur","gloss":"Bactrian camel ox and sheep and goats for not number receive","word_count":8},{"line_label":"i 15'","line_ref":"Q003448.56","transliteration":"ina ta-a-a-ar-ti-ia\u2082 {m}ir-an-su {KUR}ma-na-a-a qur-di ta-nit-te","gloss":"during return king of Mannea Mannean heroism praise","word_count":6},{"line_label":"i 16'","line_ref":"Q003448.57","transliteration":"\u0161a\u2082 a\u0161-\u0161ur EN-ia\u2082 \u0161a\u2082 a-na EN.URU.ME\u0160 EN.URU.ME\u0160 \u0161a\u2082 KUR-e DU\u2083-\u0161u\u2082-nu A\u2082-pu-\u0161a\u2082 i\u0161-me-ma","gloss":"of 1 lord that to lord lord of mountain all do hear","word_count":12},{"line_label":"i 17'","line_ref":"Q003448.58","transliteration":"hur-ba-\u0161u\u2082 UGU-\u0161u\u2082 it-ta-bi-ik-ma a-na {URU}su-um-bi i-te-e KUR a\u0161-\u0161ur{KI}","gloss":"terror over heap up//pour to boundary land Assyria","word_count":8},{"line_label":"i 18'","line_ref":"Q003448.59","transliteration":"a-di mah-ri-ia DU-ka-am-ma u\u2082-na-\u0161i-qa GIR\u2083.II-ia\u2082 AN\u0160E.KUR.RA.ME\u0160","gloss":"to front go kiss foot horse","word_count":6},{"line_label":"i 19'","line_ref":"Q003448.60","transliteration":"BABBAR.ME\u0160 GUN\u2083.ME\u0160 har-\u0161a\u2082-a-a har-x UZU-\u0161u\u2082-nu a-di ta-lul-ti-\u0161u\u2082-nu x x","gloss":"white multicoloured of Har\u0161u flesh//skin with trappings","word_count":9},{"line_label":"i 20'","line_ref":"Q003448.61","transliteration":"GU\u2084.MAH.ME\u0160 MAH.ME\u0160 \u0161u-\u02bee-e ma-ru-u-ti ma x x x-da x-\u0161u\u2082 am-hur","gloss":"prize bull exalted sheep fattened receive","word_count":10},{"line_label":"i 21'","line_ref":"Q003448.62","transliteration":"ina 3-\u0161i BALA-ia\u2082 {m}ma-ti-il\u2083 DUMU {m}a-tar-\u0161um\u2082-qa bar-tu na-bal-kat-tu\u2082","gloss":"during reign (of a king)//regnal year king of Arpad son ruler of Arpad revolt crossing//insurrection","word_count":8},{"line_label":"i 22'","line_ref":"Q003448.63","transliteration":"a-na KUR a\u0161-\u0161ur DU\u2083-ma u\u2082-ha-\u1e6da-a x LUGAL.ME\u0160 \u0161a\u2082 a-na x x.ME\u0160 \u0161a {KUR}hat-ti","gloss":"to land Assyria make do wrong//violate king who to of Syria-Palestine","word_count":13},{"line_label":"i 23'","line_ref":"Q003448.64","transliteration":"x ud a ku {KUR}URI ze-rat KUR a\u0161-\u0161ur x-ma u\u2082-\u0161am-ki-ir ma-ti-tan","gloss":"1 hostilities land Assyria be(come) different//cause enmity between in all lands","word_count":11},{"line_label":"i 24'","line_ref":"Q003448.65","transliteration":"{m}{d}INANNA-du-ri {KUR}URI-a-a {m}su-lu-ma-al {KUR}me-li-da-a-a {m}tar-qu\u2082-la-ru","gloss":"Sarduri, king of Urar\u1e6du of Urar\u1e6du king of Melid of Melid king of Gurgum","word_count":5},{"line_label":"i 25'","line_ref":"Q003448.66","transliteration":"{KUR}gur\u2082-gu-ma-a-a a-na kit-ri-\u0161u\u2082 il-li-ku i-na bi-rit {KUR}ki\u0161-tan u {KUR}hal-pi","gloss":"of Gurgum to help go in between and","word_count":9},{"line_label":"i 26'","line_ref":"Q003448.67","transliteration":"na-ge-e \u0161a {KUR}ku-muh-hi a-na e-muq a-ha-me\u0161 it-tak-lu-ma","gloss":"region of to strength one another trust","word_count":7},{"line_label":"i 27'","line_ref":"Q003448.68","transliteration":"i\u0161-kunu si-dir-tu\u2082 7 KASKAL.GID\u2082 qaq-qa-ru GE\u2086 u ur-ru","gloss":"put//establish row//line of battle double hour distance night and day","word_count":8},{"line_label":"i 28'","line_ref":"Q003448.69","transliteration":"al-li-ka-am-ma ERIM.HI.A-at KUR a\u0161-\u0161ur{KI} ul u\u2082-\u0161ap-\u0161i-ih-ma","gloss":"go military force//troops land Assyria not be(come) at rest//allow to rest","word_count":6},{"line_label":"i 29'","line_ref":"Q003448.70","transliteration":"A.ME\u0160 ul a\u0161\u2082-qi\u2082 u\u0161-ma-ni ul GAR-un-ma ul ak-\u1e63u-ra","gloss":"water not give to drink//give (drink) to camp not put//establish not tie//construct","word_count":8},{"line_label":"i 30'","line_ref":"Q003448.71","transliteration":"KARA\u0160-\u0161i ERIM.HI.A-ia an-hu-su-nu TA-\u0161u\u2082-nu am-da-hi-i\u1e63","gloss":"military camp troops tiredness with fight","word_count":5},{"line_label":"i 31'","line_ref":"Q003448.72","transliteration":"BAD\u2085.BAD\u2085-\u0161u\u2082-nu GAR-un u\u0161-ma-ni KARA\u0160-su-nu e-kim-\u0161u\u2082-nu-ti","gloss":"defeat establish camp military camp take away","word_count":5},{"line_label":"i 32'","line_ref":"Q003448.73","transliteration":"a-na \u0161u-zu-ub ZI.ME\u0160-\u0161u-nu ZAH\u2082.ME\u0160-ma","gloss":"to saving throat//life be(come) lost//escape","word_count":4},{"line_label":"i 33'","line_ref":"Q003448.74","transliteration":"{m}{d}15-BAD\u2083 {KUR}URI-a-a e-de-nu-u\u0161-\u0161u ina MUNUS.AN\u0160E.KUR.RA U\u2085-ma","gloss":"Sarduni, king of Urar\u1e6du of Urar\u1e6du alone on mare ride","word_count":6},{"line_label":"i 34'","line_ref":"Q003448.75","transliteration":"GE\u2086-i\u0161 ip-pa\u2082-ri\u0161-ma x x \u0161e ir x","gloss":"at night fly","word_count":7},{"line_label":"i 35'","line_ref":"Q003448.76","transliteration":"\u0161a\u2082 ki-i pa-\u0161ul-ti x a-na x","gloss":"who like (a crawling creature) to","word_count":6},{"line_label":"i 36'","line_ref":"Q003448.77","transliteration":"pa-qut-ti ed-de-ti mu-\u0161ah\u2082-x x","gloss":"thorn (a kind of thorn-bush)","word_count":4},{"line_label":"i 37'","line_ref":"Q003448.78","transliteration":"ip-\u0161il-ma e-li a-na KUR-\u0161u\u2082 GUR-ur TA {URU}hu-ti-x at-tu-mu\u0161","gloss":"crawl ascend to land turn//return from set (oneself) in motion","word_count":8},{"line_label":"i 38'","line_ref":"Q003448.79","transliteration":"1 ME URU.ME\u0160 \u0161a\u2082 {m}tar-hu-la-ri {KUR}gur\u2082-gu-ma-a-a ak-tu\u2082-um x","gloss":"(one) hundred city of king of Gurgum of Gurgum cover","word_count":8},{"line_label":"i 39'","line_ref":"Q003448.80","transliteration":"a-di URU.ME\u0160 \u0161a\u2082 si-hir-ti-\u0161u\u2082-nu KUR-ud {m}tar-hu-la-ri x","gloss":"with city of surroundings conquer king of Gurgum","word_count":7},{"line_label":"i 40'","line_ref":"Q003448.81","transliteration":"a-di SAG.KAL.ME\u0160 \u0161a KUR-\u0161u\u2082 it-ti ku-dur-ru-\u0161u\u2082-nu a-di mah-ri-ia il-li-ku-nim-ma","gloss":"with first and foremost one//official of land with carrying frame to front go","word_count":9},{"line_label":"i 41'","line_ref":"Q003448.82","transliteration":"u\u2082-na-\u0161i-qu GIR\u2083.II-ia\u2082 a-na la hu-lu-uq {KUR}gur\u2082-gu-me x","gloss":"kiss foot to not be(come) lost//destroying 1","word_count":7},{"line_label":"i 42'","line_ref":"Q003448.83","transliteration":"am-hur-\u0161u\u2082 TA {KUR}gur\u2082-gu-me at-tu-mu\u0161 a-na URU.ME\u0160 x","gloss":"face//receive from 1 set (oneself) in motion to city","word_count":7},{"line_label":"i 43'","line_ref":"Q003448.84","transliteration":"ad-ka u\u0161-ma-nu {URU}ka-da-mu {URU}al-x x","gloss":"raise//muster camp","word_count":5},{"line_label":"ii 1'","line_ref":"Q003448.88","transliteration":"a-di {URU}x x","gloss":"to","word_count":3},{"line_label":"ii 2'","line_ref":"Q003448.89","transliteration":"{URU}E\u2082-bar-ru-a x","gloss":"1","word_count":2},{"line_label":"ii 3'","line_ref":"Q003448.90","transliteration":"a-di {KUR}ni-qi \u0161a\u2082 {KUR}tup-li-a\u0161\u2082 x","gloss":"to of","word_count":5},{"line_label":"ii 4'","line_ref":"Q003448.91","transliteration":"{KUR}E\u2082-a-gu-si a-na si-hir-ti-\u0161u\u2082","gloss":"1 to entirety","word_count":3},{"line_label":"ii 5'","line_ref":"Q003448.92","transliteration":"{KUR}pat-ti-nu a-na si-hir-ti-\u0161u\u2082 TA {URU}x x","gloss":"to entirety from","word_count":6},{"line_label":"ii 6'","line_ref":"Q003448.93","transliteration":"{URU}na-an-pi-gi \u0161a GU\u2082 {ID\u2082}A.\u0160ITA\u2083 x","gloss":"1 that neck//bank Euphrates","word_count":5},{"line_label":"ii 7'","line_ref":"Q003448.94","transliteration":"{URU}qar-ne\u2082-e {URU}ha-da-te-te {URU}da-x","gloss":"","word_count":3},{"line_label":"ii 8'","line_ref":"Q003448.95","transliteration":"{URU}qi-na-as-ri-na \u0161a\u2082 ma-ad-ba-ri EN","gloss":"of steppe//desert to","word_count":4},{"line_label":"ii 9'","line_ref":"Q003448.96","transliteration":"{URU}di-ma\u0161-qi {KUR}ha-mat","gloss":"Damascus Hamath","word_count":2},{"line_label":"ii 10'","line_ref":"Q003448.97","transliteration":"{KUR}ha-su-at-ti {KUR}\u1e6du-ri-na-qa-di-na {KUR}si-an-nu ana pa\u1e6d gim-ri-\u0161i-na","gloss":"1 to border totality","word_count":6},{"line_label":"ii 11'","line_ref":"Q003448.98","transliteration":"{URU}el-li-\u0161u\u2082 {URU}\u1e63i-mi\u2083-ra \u0161a\u2082 GIR\u2083.II {KUR}lab-na-na","gloss":"that foot Mount Lebanon","word_count":5},{"line_label":"ii 12'","line_ref":"Q003448.99","transliteration":"{URU}SAG-\u1e63ur-ri {KUR}\u1e63a-pu-na {URU}ah-ta-a","gloss":"1 Mount \u1e62apuna","word_count":3},{"line_label":"ii 13'","line_ref":"Q003448.100","transliteration":"E\u2082 ka-ri \u0161a\u2082 UGU tam-tim E\u2082 \u1e63a-bu-ta-te MAN-ti KUR {GI\u0160}TUG\u2082","gloss":"house quay that on sea house wish//what is needed kingship land boxwood","word_count":10},{"line_label":"ii 14'","line_ref":"Q003448.101","transliteration":"{URU}tu-\u02bea-am-mu EN {URU}DU\u2086-kar-me \u0161a\u2082 {KUR}gur\u2082-gu-me","gloss":"to 1 of 1","word_count":5},{"line_label":"ii 15'","line_ref":"Q003448.102","transliteration":"ana mi-\u1e63ir KUR a\u0161-\u0161ur GUR-er UGU mi-\u1e63ir KUR a\u0161-\u0161ur KUR.KUR","gloss":"to border land Assyria turn//return over border land Assyria land","word_count":10},{"line_label":"ii 16'","line_ref":"Q003448.103","transliteration":"u\u2082-\u0161a\u2082-tir DAB-bat UGU UN.ME\u0160-\u0161a\u2082 UN.ME\u0160 ana la ma-ni u\u2082-rad-di","gloss":"make bigger seize to people people for not counting add","word_count":9},{"line_label":"ii 17'","line_ref":"Q003448.104","transliteration":"a-bur-ri\u0161 ar-te-ne\u2082-\u02beu-u\u2082-\u0161i-na-a-ti","gloss":"in a green pasture tend cattle//shepherd","word_count":2},{"line_label":"ii 18'","line_ref":"Q003448.105","transliteration":"ana-ku {m}tukul-ti-A-e\u2082-\u0161ar\u2082 MAN KUR a\u0161-\u0161ur \u0161a\u2082 TA E\u2083 {d}UTU-\u0161i","gloss":"I Tiglath-pileser III, king of Assyria king land Assyria who from exit sun","word_count":9},{"line_label":"ii 19'","line_ref":"Q003448.106","transliteration":"EN \u0160U\u2082 {d}UTU-\u0161i KUR.ME\u0160 DU\u2083-\u0161i-na \u0160U.II-ia\u2082 ik-\u0161u\u2082-da","gloss":"to (sun)set sun mountain all hand reach//conquer","word_count":7},{"line_label":"ii 20'","line_ref":"Q003448.107","transliteration":"KI MAN.ME\u0160-ni AD.ME\u0160-a la e-ti-qa","gloss":"place king father//ancestor not cross over","word_count":5},{"line_label":"ii 21'","line_ref":"Q003448.108","transliteration":"{GI\u0160}mu-ger-ra-\u0161u\u2082-nu a\u0161\u2082-ta-kan {LU\u2082}GAR.ME\u0160","gloss":"two-wheeled vehicle//chariot put//place governor","word_count":3},{"line_label":"ii 22'","line_ref":"Q003448.109","transliteration":"TA tam-ti GAL-ti \u0161a\u2082 E\u2083 \u0161am-\u0161i EN {URU}SAG-\u1e63u-ri","gloss":"from sea great of exit sun to","word_count":8},{"line_label":"ii 23'","line_ref":"Q003448.110","transliteration":"{URU}gub-li \u0161a\u2082 GU\u2082 tam-ti GAL-ti \u0161a\u2082 SILIM \u0161am-\u0161i","gloss":"Byblos that shore sea great of completeness sun","word_count":8},{"line_label":"ii 24'","line_ref":"Q003448.111","transliteration":"DU.DU-ku-ma a-be\u2082-lu kib-rata","gloss":"go//march rule (over) bank//quarter","word_count":3},{"line_label":"ii 25'","line_ref":"Q003448.112","transliteration":"ina 9 BALA.ME\u0160-ia\u2082 a-na mada-a-a DU-ku aq-bi","gloss":"during reign (of a king)//regnal year to Median marching command","word_count":7},{"line_label":"ii 26'","line_ref":"Q003448.113","transliteration":"\u0161a\u2082 EN.ME\u0160 URU.ME\u0160 la GUR\u2082-\u0161u-ti URU.ME\u0160-\u0161u\u2082-nu KUR-ud","gloss":"of lord city not submissive city conquer","word_count":7},{"line_label":"ii 27'","line_ref":"Q003448.114","transliteration":"di-ik-ta-\u0161u\u2082-nu a-duk \u0161al-la-su-nu a\u0161\u2082-lu-la","gloss":"defeat defeat booty carry off","word_count":4},{"line_label":"ii 28'","line_ref":"Q003448.115","transliteration":"ina x {URU}E\u2082-{d}INANNA {URU}\u1e63i-bar {KUR}a-ri-ar-ma {KUR}sil-ha-zu","gloss":"in Mount Ariarma Mount Silhazi","word_count":6},{"line_label":"ii 29'","line_ref":"Q003448.116","transliteration":"KUR-e KAL.ME\u0160 NAR.ME\u0160-ia\u2082 u\u2082-kin \u0161a\u2082 GUR\u2082-\u0161u\u2082-te ma-da-ta-\u0161u\u2082-nu am-hur","gloss":"mountain strong stele establish firmly of submissive one payment receive","word_count":8},{"line_label":"ii 30'","line_ref":"Q003448.117","transliteration":"1 ME 30+x AN\u0160E.KUR.RA.ME\u0160 {URU}E\u2082-15 a-di na-gi-\u0161u\u2082 am-hur","gloss":"(one) hundred horse with region receive","word_count":8},{"line_label":"ii 31'","line_ref":"Q003448.118","transliteration":"1 ME 20 {URU}gi-ni-zi-na-nu {URU}sad-bat {URU}si-sa-ad-x","gloss":"(one) hundred","word_count":6},{"line_label":"ii 32'","line_ref":"Q003448.119","transliteration":"1 ME {m}u\u2082-pa-a\u0161\u2082 DUMU {m}kap-si 1 ME {m}u\u0161-ru-u\u2082 \u0161a\u2082 {KUR}ni-ki-si","gloss":"(one) hundred ruler of Bit-Kapsi son Kapsu (one) hundred ruler of Nikisi of","word_count":10},{"line_label":"ii 33'","line_ref":"Q003448.120","transliteration":"1 ME {m}uk-sa-tar \u0161a\u2082 {URU}qar-kin-\u0161e-ra 1 ME {m}ia-u\u2082-bit-ir \u0161a\u2082 {KUR}a-mat","gloss":"(one) hundred ruler of Qarkin\u0161era of (one) hundred ruler of Amate of","word_count":10},{"line_label":"ii 34'","line_ref":"Q003448.121","transliteration":"3 ME {m}bar-da-da \u0161a\u2082 {URU}\u1e63i-bar 33 {m}a-ma-ku \u0161a\u2082 {URU}kit-ku-x","gloss":"(one) hundred ruler of \u1e62ibar of ruler of Kitku-x of","word_count":9},{"line_label":"ii 35'","line_ref":"Q003448.122","transliteration":"32 {m}\u0161a\u2082-ta-qu-pi \u0161a\u2082 {URU}u\u2082-pa-ri-a","gloss":"ruler of Uppuria of 1","word_count":4},{"line_label":"ii 36'","line_ref":"Q003448.123","transliteration":"1 ME {m}ra-ma-te-ia \u0161a\u2082 {URU}ka-zu-qin-za-ni","gloss":"(one) hundred ruler of Arazia\u0161 of","word_count":5},{"line_label":"ii 37'","line_ref":"Q003448.124","transliteration":"1 ME {m}me-et-ra-ku \u0161a\u2082 {URU}u\u2082-pa-ri-a","gloss":"(one) hundred ruler of Uppuria of 1","word_count":5},{"line_label":"ii 38'","line_ref":"Q003448.125","transliteration":"2 ME {m}\u0161a\u2082-ta-a\u0161\u2082-pa \u0161a\u2082 {URU}\u0161a-pa-ar-da","gloss":"(one) hundred ruler of Saparda of 1","word_count":5},{"line_label":"ii 39'","line_ref":"Q003448.126","transliteration":"1 ME {m}u\u2082-i-ta-na \u0161a\u2082 {URU}mi-\u0161i-ta","gloss":"(one) hundred ruler of Mi\u0161ita of","word_count":5},{"line_label":"ii 40'","line_ref":"Q003448.127","transliteration":"1 ME {m}a-mi\u2083-ta-na \u0161a\u2082 {URU}u\u2082-i-zak-x","gloss":"(one) hundred ruler of Uizak-x of","word_count":5},{"line_label":"ii 41'","line_ref":"Q003448.128","transliteration":"x x {m}\u0161a-ta-par-nu-u \u0161a\u2082 {URU}ur-ba-x","gloss":"ruler of Urba-x of","word_count":5},{"line_label":"ii 42'","line_ref":"Q003448.129","transliteration":"x-x-ba-a \u0161a\u2082 {URU}sik-ra-a","gloss":"of","word_count":3},{"line_label":"ii 43'","line_ref":"Q003448.130","transliteration":"x-ia \u0161a\u2082 {URU}zak-ru-te","gloss":"of 1","word_count":3},{"line_label":"ii 44'","line_ref":"Q003448.131","transliteration":"x \u0161a\u2082 {URU}a-ku-x-x","gloss":"of","word_count":3},{"line_label":"iii 1","line_ref":"Q003448.134","transliteration":"MAN.ME\u0160 \u0161a\u2082 {KUR}hat-ti {KUR}a-ri-me \u0161a\u2082 U\u0160 tam-tim","gloss":"king of Syria-Palestine Aram that side//shore sea","word_count":7},{"line_label":"iii 2","line_ref":"Q003448.135","transliteration":"\u0161a\u2082 SILIM {d}\u0161am-\u0161i {KUR}qid-ri {KUR}a-ri-bi","gloss":"of completeness sun Qedar Arabia","word_count":5},{"line_label":"iii 3","line_ref":"Q003448.136","transliteration":"{m}ku\u0161-ta\u0161-pi {URU}ku-muh-a-a","gloss":"king of Kummuhu of Kummuhu","word_count":2},{"line_label":"iii 4","line_ref":"Q003448.137","transliteration":"{m}ra-qi-a-nu {KUR}\u0161a\u2082-AN\u0160E.NITA\u2082-\u0161u\u2082-a-a","gloss":"Rezin, king of Damascus of Damascus","word_count":2},{"line_label":"iii 5","line_ref":"Q003448.138","transliteration":"{m}mi-ni-hi-im-me {KUR}sa-me-ri-i-na-a-a","gloss":"Menahem, king of Israel of Samaria","word_count":2},{"line_label":"iii 6","line_ref":"Q003448.139","transliteration":"{m}tu-ba-il\u2083 {URU}\u1e63ur-a-a","gloss":"king of Tyre of Tyre","word_count":2},{"line_label":"iii 7","line_ref":"Q003448.140","transliteration":"{m}si-bit\u2082-ba-il\u2083 {KUR}gub-la-a-a","gloss":"ruler of Byblos of Byblos","word_count":2},{"line_label":"iii 8","line_ref":"Q003448.141","transliteration":"{m}u\u2082-ri-ik {KUR}qu-u\u2082-a-a","gloss":"king of Que of Que","word_count":2},{"line_label":"iii 9","line_ref":"Q003448.142","transliteration":"{m}su-lu-mal {KUR}mi-lid-a-a","gloss":"king of Melid of Melid","word_count":2},{"line_label":"iii 10","line_ref":"Q003448.143","transliteration":"{m}u\u2082-as-sur-me {KUR}ta-bal-a-a","gloss":"ruler of Tabal of Tabal","word_count":2},{"line_label":"iii 11","line_ref":"Q003448.144","transliteration":"{m}u\u0161-hi-ti {KUR}a-tu\u2082-na-a-a","gloss":"ruler of Atuna of Atuna","word_count":2},{"line_label":"iii 12","line_ref":"Q003448.145","transliteration":"{m}ur-pal-la-a {KUR}tu\u2082-ha-na-a-a","gloss":"ruler of Tuhana of Tuhana","word_count":2},{"line_label":"iii 13","line_ref":"Q003448.146","transliteration":"{m}tu\u2082-ha-me {KUR}i\u0161-tu-un-di-a-a","gloss":"ruler of I\u0161tunda of I\u0161tunda","word_count":2},{"line_label":"iii 14","line_ref":"Q003448.147","transliteration":"{m}u\u2082-i-ri-mi {KUR}hu-bi-i\u0161-na-a-a","gloss":"ruler of Que of Hubu\u0161nu","word_count":2},{"line_label":"iii 15","line_ref":"Q003448.148","transliteration":"{m}da-di-il\u2083 {KUR}kas\u2082-ka-a-a","gloss":"chief of the Kasku of Kaska","word_count":2},{"line_label":"iii 16","line_ref":"Q003448.149","transliteration":"{m}pi-si-ri-is {URU}gar-ga-mi\u0161-a-a","gloss":"king of Carchemish of Carchemish","word_count":2},{"line_label":"iii 17","line_ref":"Q003448.150","transliteration":"{m}pa-na-am-mu {KUR}sa-ma-al-la-a-a","gloss":"king of Sam\u02beal of Sam\u02beal","word_count":2},{"line_label":"iii 18","line_ref":"Q003448.151","transliteration":"{m}tar-hu-la-ru {KUR}gur\u2082-gu-ma-a-a","gloss":"king of Gurgum of Gurgum","word_count":2},{"line_label":"iii 19","line_ref":"Q003448.152","transliteration":"{f}za-bi-be\u2082-e \u0161ar-rat {KUR}a-ri-bi","gloss":"queen of the Arabs queen Arabia","word_count":3},{"line_label":"iii 20","line_ref":"Q003448.153","transliteration":"bil\u2082-tu\u2082 ma-da-tu\u2082 KU\u2083.BABBAR KU\u2083.GI AN.NA AN.BAR","gloss":"tribute payment silver gold tin iron","word_count":6},{"line_label":"iii 21","line_ref":"Q003448.154","transliteration":"KU\u0160 AM.SI ZU\u2082 AM.SI ta-kil-tu\u2082 ar-ga-man-nu","gloss":"skin elephant tooth elephant (a precious blue-purple wool) purple","word_count":6},{"line_label":"iii 22","line_ref":"Q003448.155","transliteration":"lu-bul-ti bir-me GADA AN\u0160E.A.AB.BA.ME\u0160","gloss":"clothing multicoloured cloth linen camel","word_count":4},{"line_label":"iii 23","line_ref":"Q003448.156","transliteration":"{AN\u0160E}a-na-qa-a-ti UGU-\u0161u\u2082-nu u\u2082-kin","gloss":"she-camels over establish firmly","word_count":3},{"line_label":"iii 24","line_ref":"Q003448.157","transliteration":"u\u2083 \u0161a\u2082 {m}ir-an-zi {KUR}man-na-a-a","gloss":"and of king of Mannea Mannean","word_count":4},{"line_label":"iii 25","line_ref":"Q003448.158","transliteration":"{m}dal-ta-a {KUR}el-lip\u2082-a-a","gloss":"king of Ellipi of Ellipi","word_count":2},{"line_label":"iii 26","line_ref":"Q003448.159","transliteration":"EN.URU.ME\u0160 EN.URU.ME\u0160 \u0161a\u2082 {KUR}ZALAG\u2082 {KUR}sin-gi-bu-ta-a-a","gloss":"lord lord of of Bit-Sangibutu","word_count":5},{"line_label":"iii 27","line_ref":"Q003448.160","transliteration":"\u0161a\u2082 KUR-e DU\u2083-\u0161u\u2082-nu \u0161a\u2082 KUR {d}\u0161am-\u0161i","gloss":"of mountain all of rising sun","word_count":6},{"line_label":"iii 28","line_ref":"Q003448.161","transliteration":"AN\u0160E.KUR.RA.ME\u0160 pa-re-e {AN\u0160E}ud-ra-te","gloss":"horse mule Bactrian camel","word_count":3},{"line_label":"iii 29","line_ref":"Q003448.162","transliteration":"GU\u2084.ME\u0160 \u1e63e-e-ni UGU-\u0161u\u2082-nu-ma u\u2082-kin","gloss":"ox sheep and goats on//over establish firmly","word_count":4},{"line_label":"iii 30","line_ref":"Q003448.163","transliteration":"\u0161at-ti-\u0161am-ma am-da-na-ha-ra ina qe\u2082-reb KUR a\u0161-\u0161ur{KI}","gloss":"yearly face//receive constantly in interior land Assyria","word_count":6},{"line_label":"iii 31","line_ref":"Q003448.164","transliteration":"u\u2082-\u0161e-pi\u0161-ma {NA\u2084}NA.RU\u2082.A ina NIGIN KUR-e","gloss":"make stele in circumference//surroundings mountain","word_count":5},{"line_label":"iii 32","line_ref":"Q003448.165","transliteration":"DINGIR.ME\u0160 GAL.ME\u0160 EN.ME\u0160-ia\u2082 ina muh-hi e-\u1e63i-ir","gloss":"god great lord on skull draw","word_count":6},{"line_label":"iii 33","line_ref":"Q003448.166","transliteration":"NU MAN-ti-ia\u2082 ina qer-bi-\u0161u\u2082 ab-ni-ma","gloss":"effigy//image kingship in interior create","word_count":5},{"line_label":"iii 34","line_ref":"Q003448.167","transliteration":"li-ta-at a\u0161-\u0161ur EN-ia\u2082 u\u2083 KUR \u0160U.II-ia\u2082","gloss":"victory 1 lord and achievement//conquest hand","word_count":6},{"line_label":"iii 35","line_ref":"Q003448.168","transliteration":"\u0161a\u2082 ina KUR.KUR A\u2082-pu-\u0161a\u2082 ina muh-hi a\u0161\u2082-\u1e6dur","gloss":"that in land do on skull write","word_count":7},{"line_label":"iii 36","line_ref":"Q003448.169","transliteration":"ina mi-i\u1e63-ri \u0161a\u2082 a-na x x","gloss":"on border that to","word_count":6},{"line_label":"iii 1'","line_ref":"Q003448.171","transliteration":"{NA\u2084}NA.RU\u2082.A x","gloss":"stele","word_count":2},{"line_label":"iii 2'","line_ref":"Q003448.172","transliteration":"DINGIR.ME\u0160 GAL.ME\u0160 a-\u0161i-bu-ut AN-e KI-tim","gloss":"god great inhabitant heaven earth//netherworld","word_count":5},{"line_label":"iii 3'","line_ref":"Q003448.173","transliteration":"ma-la ina {NA\u2084}NA.RU\u2082-e \u0160E\u0160-e MU-\u0161u-nu zak-ru","gloss":"as much as on stele this name named","word_count":6},{"line_label":"iii 4'","line_ref":"Q003448.174","transliteration":"{GI\u0160}GU.ZA-\u0161u\u2082 li-su-hu BALA-\u0161u\u2082 lis-ki-pu","gloss":"throne remove dynasty push down//overthrow","word_count":4},{"line_label":"iii 5'","line_ref":"Q003448.175","transliteration":"KUR-su lu-te-ru a-na DU\u2086 u kar-me","gloss":"land turn//turn into to (ruin) mound and heap","word_count":6},{"line_label":"iii 6'","line_ref":"Q003448.176","transliteration":"NUN EGIR-u {NA\u2084}NA.RU\u2082.A \u0161u-a-tu\u2082","gloss":"ruler later stele that","word_count":4},{"line_label":"iii 7'","line_ref":"Q003448.177","transliteration":"lil\u2082-ta-si-ma A.ME\u0160 li-ra-mi-ik-ma","gloss":"read aloud water bathe oneself//wash","word_count":3},{"line_label":"iii 8'","line_ref":"Q003448.178","transliteration":"I\u2083.ME\u0160 lip-\u0161u-u\u0161 {UDU}SISKUR liq-qi\u2082","gloss":"oil anoint offering make (an offering)","word_count":4},{"line_label":"iii 9'","line_ref":"Q003448.179","transliteration":"DINGIR.ME\u0160 \u0161u-a-tu\u2082-nu","gloss":"god those","word_count":2},{"line_label":"iii 10'","line_ref":"Q003448.180","transliteration":"ik-ri-be\u2082-e-\u0161u\u2082 \u0160E.GA-u\u2082","gloss":"prayer hear","word_count":2}],"akkadian_words":[{"form":"a\u0161-\u0161ur","cf":"A\u0161\u0161ur","gw":"1","pos":"DN","lang":"akk","line_ref":"Q003448.3","position":0},{"form":"EN","cf":"b\u0113lu","gw":"lord","pos":"$","lang":"akk","line_ref":"Q003448.3","position":1},{"form":"GAL","cf":"rab\u00fb","gw":"great","pos":"AJ","lang":"akk","line_ref":"Q003448.3","position":2},{"form":"{d}EN.LIL\u2082.LA\u2082","cf":"Enlil","gw":"1","pos":"DN","lang":"akk","line_ref":"Q003448.3","position":3},{"form":"DINGIR.ME\u0160","cf":"il\u0101ni","gw":"god","pos":"N","lang":"akk","line_ref":"Q003448.3","position":4},{"form":"mu-\u0161i-me","cf":"mu\u0161immu","gw":"one who determines","pos":"N$mu\u0161imme","lang":"akk","line_ref":"Q003448.3","position":5},{"form":"NAM.ME\u0160","cf":"\u0161\u012bm\u0101ti","gw":"fate","pos":"N","lang":"akk","line_ref":"Q003448.3","position":6},{"form":"{d}AMAR.UTU","cf":"Marduk","gw":"1","pos":"DN","lang":"akk","line_ref":"Q003448.4","position":0},{"form":"mu\u0161-te-\u0161ir","cf":"mu\u0161t\u0113\u0161ir","gw":"one who sets straight","pos":"N","lang":"akk","line_ref":"Q003448.4","position":1},{"form":"GI\u0160.HUR","cf":"u\u1e63urtu","gw":"drawing//plan","pos":"N$u\u1e63ur\u0101ti","lang":"akk","line_ref":"Q003448.4","position":2},{"form":"DU\u2083-ni-u","cf":"b\u0101n\u00fb","gw":"creator","pos":"N$b\u0101ni\u02beu","lang":"akk","line_ref":"Q003448.4","position":3},{"form":"mit-hur-ti","cf":"mithurtu","gw":"convergence//harmony","pos":"N$mithurti","lang":"akk","line_ref":"Q003448.4","position":4},{"form":"pa-qid","cf":"p\u0101qid","gw":"carer","pos":"N","lang":"akk","line_ref":"Q003448.4","position":5},{"form":"x","cf":"","gw":"","pos":"","lang":"akk","line_ref":"Q003448.5","position":0},{"form":"mu-u\u2082-kin","cf":"mukinnu","gw":"witness//one who firmly establishes","pos":"N$muk\u012bn","lang":"akk","line_ref":"Q003448.5","position":1},{"form":"i\u0161-di","cf":"i\u0161du","gw":"foundation","pos":"N$i\u0161d\u012b","lang":"akk","line_ref":"Q003448.5","position":2},{"form":"KUR","cf":"m\u0101ti","gw":"land","pos":"N","lang":"akk","line_ref":"Q003448.5","position":3},{"form":"{d}AG","cf":"Nabu","gw":"1","pos":"DN","lang":"akk","line_ref":"Q003448.6","position":0},{"form":"ta-mi-ih","cf":"t\u0101mih","gw":"one who grasps","pos":"N","lang":"akk","line_ref":"Q003448.6","position":1},{"form":"GI.DUB","cf":"gidubb\u00fb","gw":"stylus","pos":"N$gidubb\u00ea","lang":"akk","line_ref":"Q003448.6","position":2},{"form":"na-\u0161i","cf":"n\u0101\u0161i","gw":"bearer","pos":"N","lang":"akk","line_ref":"Q003448.6","position":3},{"form":"DUB","cf":"\u1e6duppu","gw":"tablet","pos":"N$\u1e6duppi","lang":"akk","line_ref":"Q003448.6","position":4},{"form":"\u0161i-mat","cf":"\u0161\u012bmtu","gw":"what is fixed//fate","pos":"N$\u0161\u012bm\u0101t","lang":"akk","line_ref":"Q003448.6","position":5},{"form":"DINGIR.DINGIR","cf":"il\u0101ni","gw":"god","pos":"N","lang":"akk","line_ref":"Q003448.6","position":6},{"form":"x","cf":"","gw":"","pos":"","lang":"akk","line_ref":"Q003448.7","position":0},{"form":"{d}U.GUR","cf":"Nergal","gw":"1","pos":"DN","lang":"akk","line_ref":"Q003448.7","position":1},{"form":"GIR\u2083.GIR\u2083.GIR\u2083","cf":"","gw":"","pos":"","lang":"akk","line_ref":"Q003448.7","position":2},{"form":"x","cf":"","gw":"","pos":"","lang":"akk","line_ref":"Q003448.8","position":0},{"form":"\u0161a\u2082","cf":"\u0161a","gw":"who","pos":"REL","lang":"akk","line_ref":"Q003448.8","position":1},{"form":"la","cf":"l\u0101","gw":"not","pos":"MOD","lang":"akk","line_ref":"Q003448.8","position":2},{"form":"IGI-ru","cf":"mah\u0101ru","gw":"face//be faced","pos":"V$immaharu","lang":"akk","line_ref":"Q003448.8","position":3},{"form":"qa-bal-\u0161u\u2082","cf":"qabal\u0161u","gw":"battle","pos":"N","lang":"akk","line_ref":"Q003448.8","position":4},{"form":"{d}UTU","cf":"\u0160ama\u0161","gw":"1","pos":"DN","lang":"akk","line_ref":"Q003448.9","position":0},{"form":"\u0161a-ki-ni","cf":"\u0161\u0101kinu","gw":"one who places","pos":"N$\u0161\u0101kini","lang":"akk","line_ref":"Q003448.9","position":1},{"form":"GI\u0160.MI","cf":"\u1e63illu","gw":"shade//protection","pos":"N$\u1e63illi","lang":"akk","line_ref":"Q003448.9","position":2},{"form":"x","cf":"","gw":"","pos":"","lang":"akk","line_ref":"Q003448.9","position":3},{"form":"x","cf":"","gw":"","pos":"","lang":"akk","line_ref":"Q003448.9","position":4},{"form":"x","cf":"","gw":"","pos":"","lang":"akk","line_ref":"Q003448.9","position":5},{"form":"ME\u0160","cf":"","gw":"","pos":"","lang":"akk","line_ref":"Q003448.9","position":6},{"form":"{d}30","cf":"Sin","gw":"1","pos":"DN","lang":"akk","line_ref":"Q003448.10","position":0},{"form":"na-an-na-ru","cf":"nann\u0101ru","gw":"light of the sky","pos":"N$","lang":"akk","line_ref":"Q003448.10","position":1},{"form":"nam-ru","cf":"namru","gw":"bright","pos":"AJ","lang":"akk","line_ref":"Q003448.10","position":2},{"form":"na-din","cf":"n\u0101din","gw":"giver","pos":"N","lang":"akk","line_ref":"Q003448.10","position":3},{"form":"{GI\u0160}GIDRU","cf":"ha\u1e6d\u1e6di","gw":"sceptre","pos":"N","lang":"akk","line_ref":"Q003448.10","position":4},{"form":"AGA","cf":"ag\u00fb","gw":"crown","pos":"N$ag\u00ea","lang":"akk","line_ref":"Q003448.10","position":5},{"form":"mu-kin","cf":"muk\u012bn","gw":"one who firmly establishes","pos":"N","lang":"akk","line_ref":"Q003448.10","position":6},{"form":"be-lu-ti","cf":"b\u0113l\u016btu","gw":"rule//lordship","pos":"N$b\u0113l\u016bti","lang":"akk","line_ref":"Q003448.10","position":7},{"form":"{d}I\u0160KUR","cf":"Adad","gw":"1","pos":"DN","lang":"akk","line_ref":"Q003448.11","position":0},{"form":"GU\u2082.GAL","cf":"gugal","gw":"irrigation controller","pos":"N","lang":"akk","line_ref":"Q003448.11","position":1},{"form":"AN-e","cf":"\u0161am\u00ea","gw":"heaven","pos":"N","lang":"akk","line_ref":"Q003448.11","position":2},{"form":"KI-tim","cf":"er\u1e63etim","gw":"earth","pos":"N","lang":"akk","line_ref":"Q003448.11","position":3},{"form":"mu-kam\u2082-mir","cf":"mukammir","gw":"one who heaps up","pos":"N","lang":"akk","line_ref":"Q003448.11","position":4},{"form":"\u1e6duh-di","cf":"\u1e6duhdi","gw":"abundance","pos":"N","lang":"akk","line_ref":"Q003448.11","position":5},{"form":"HE\u2082.GAL\u2082","cf":"hegalli","gw":"plenty","pos":"N","lang":"akk","line_ref":"Q003448.11","position":6},{"form":"x","cf":"","gw":"","pos":"","lang":"akk","line_ref":"Q003448.11","position":7},{"form":"x","cf":"","gw":"","pos":"","lang":"akk","line_ref":"Q003448.11","position":8},{"form":"{d}e\u2082-a","cf":"Ea","gw":"1","pos":"DN","lang":"akk","line_ref":"Q003448.12","position":0},{"form":"EN","cf":"b\u0113l","gw":"lord","pos":"N","lang":"akk","line_ref":"Q003448.12","position":1},{"form":"ne\u2082-me-qi","cf":"n\u0113meqi","gw":"wisdom","pos":"N","lang":"akk","line_ref":"Q003448.12","position":2},{"form":"pa-tiq","cf":"p\u0101tiq","gw":"one who fashions","pos":"N","lang":"akk","line_ref":"Q003448.12","position":3},{"form":"kul-lat","cf":"kullat","gw":"all of","pos":"N","lang":"akk","line_ref":"Q003448.12","position":4},{"form":"mim-ma","cf":"mimma","gw":"anything","pos":"XP","lang":"akk","line_ref":"Q003448.12","position":5},{"form":"\u0161um-\u0161u\u2082","cf":"\u0161um\u0161u","gw":"name","pos":"N","lang":"akk","line_ref":"Q003448.12","position":6},{"form":"mu-ban-ni-u","cf":"mubann\u00fb","gw":"one who beautifies//one who treats well","pos":"N$mubanni\u02beu","lang":"akk","line_ref":"Q003448.12","position":7},{"form":"nab-ni-ti","cf":"nabn\u012bti","gw":"creatures","pos":"N","lang":"akk","line_ref":"Q003448.12","position":8},{"form":"{d}15","cf":"I\u0161tar","gw":"1","pos":"DN","lang":"akk","line_ref":"Q003448.13","position":0},{"form":"x","cf":"","gw":"","pos":"","lang":"akk","line_ref":"Q003448.13","position":1},{"form":"ra-i-mat","cf":"r\u0101\u02beimat","gw":"one who loves","pos":"N","lang":"akk","line_ref":"Q003448.13","position":2},{"form":"LUGAL","cf":"\u0161arri","gw":"king","pos":"N","lang":"akk","line_ref":"Q003448.13","position":3},{"form":"\u0160E.GA-\u0161a\u2082","cf":"migru","gw":"consent//favourite","pos":"N$migri\u0161a","lang":"akk","line_ref":"Q003448.13","position":4},{"form":"mu-x-x","cf":"","gw":"","pos":"","lang":"akk","line_ref":"Q003448.13","position":5},{"form":"x-ti","cf":"","gw":"","pos":"","lang":"akk","line_ref":"Q003448.13","position":6},{"form":"{d}7.BI","cf":"Sebetti","gw":"1","pos":"DN$","lang":"akk","line_ref":"Q003448.14","position":0},{"form":"EN.ME\u0160","cf":"b\u0113l\u012b","gw":"lord","pos":"N","lang":"akk","line_ref":"Q003448.14","position":1},{"form":"ge\u0161-ru-ti","cf":"ga\u0161ru","gw":"very strong","pos":"AJ$ge\u0161r\u016bti","lang":"akk","line_ref":"Q003448.14","position":2},{"form":"a-li-kut","cf":"\u0101lik\u016bt","gw":"goer","pos":"N","lang":"akk","line_ref":"Q003448.14","position":3},{"form":"pa-an","cf":"p\u0101n","gw":"front","pos":"N","lang":"akk","line_ref":"Q003448.14","position":4},{"form":"ERIM.HI-ia","cf":"umm\u0101nu","gw":"military force//troops","pos":"N$umm\u0101n\u0101tiya","lang":"akk","line_ref":"Q003448.14","position":5},{"form":"\u0160UB","cf":"mu\u0161amqitu","gw":"one who who overthrows","pos":"N$mu\u0161amqit\u016b","lang":"akk","line_ref":"Q003448.14","position":6},{"form":"x","cf":"","gw":"","pos":"","lang":"akk","line_ref":"Q003448.14","position":7},{"form":"x","cf":"","gw":"","pos":"","lang":"akk","line_ref":"Q003448.14","position":8},{"form":"x","cf":"","gw":"","pos":"","lang":"akk","line_ref":"Q003448.14","position":9},{"form":"x","cf":"","gw":"","pos":"","lang":"akk","line_ref":"Q003448.14","position":10},{"form":"x","cf":"","gw":"","pos":"","lang":"akk","line_ref":"Q003448.14","position":11},{"form":"x","cf":"","gw":"","pos":"","lang":"akk","line_ref":"Q003448.14","position":12},{"form":"{d}MAR.TU","cf":"Amurru","gw":"1","pos":"DN","lang":"akk","line_ref":"Q003448.15","position":0},{"form":"x","cf":"","gw":"","pos":"","lang":"akk","line_ref":"Q003448.15","position":1},{"form":"x","cf":"","gw":"","pos":"","lang":"akk","line_ref":"Q003448.15","position":2},{"form":"x","cf":"","gw":"","pos":"","lang":"akk","line_ref":"Q003448.15","position":3},{"form":"x","cf":"","gw":"","pos":"","lang":"akk","line_ref":"Q003448.15","position":4},{"form":"x","cf":"","gw":"","pos":"","lang":"akk","line_ref":"Q003448.15","position":5},{"form":"x","cf":"","gw":"","pos":"","lang":"akk","line_ref":"Q003448.15","position":6},{"form":"x","cf":"","gw":"","pos":"","lang":"akk","line_ref":"Q003448.15","position":7},{"form":"x","cf":"","gw":"","pos":"","lang":"akk","line_ref":"Q003448.16","position":0},{"form":"x","cf":"","gw":"","pos":"","lang":"akk","line_ref":"Q003448.16","position":1},{"form":"x","cf":"","gw":"","pos":"","lang":"akk","line_ref":"Q003448.16","position":2},{"form":"DINGIR.ME\u0160","cf":"il\u0101ni","gw":"god","pos":"N","lang":"akk","line_ref":"Q003448.17","position":0},{"form":"GAL.ME\u0160","cf":"rab\u00fbti","gw":"great","pos":"AJ","lang":"akk","line_ref":"Q003448.17","position":1},{"form":"a-\u0161i-bu-tu","cf":"\u0101\u0161ib\u016btu","gw":"inhabitant","pos":"N","lang":"akk","line_ref":"Q003448.17","position":2},{"form":"AN-e","cf":"\u0161am\u00ea","gw":"heaven","pos":"N","lang":"akk","line_ref":"Q003448.17","position":3},{"form":"KI-tim","cf":"er\u1e63etim","gw":"netherworld","pos":"N","lang":"akk","line_ref":"Q003448.17","position":4},{"form":"x","cf":"","gw":"","pos":"","lang":"akk","line_ref":"Q003448.18","position":0},{"form":"x","cf":"","gw":"","pos":"","lang":"akk","line_ref":"Q003448.18","position":1},{"form":"x","cf":"","gw":"","pos":"","lang":"akk","line_ref":"Q003448.18","position":2},{"form":"x","cf":"","gw":"","pos":"","lang":"akk","line_ref":"Q003448.19","position":0},{"form":"\u0161e","cf":"","gw":"","pos":"","lang":"akk","line_ref":"Q003448.19","position":1},{"form":"mu","cf":"","gw":"","pos":"","lang":"akk","line_ref":"Q003448.19","position":2},{"form":"x","cf":"","gw":"","pos":"","lang":"akk","line_ref":"Q003448.20","position":0},{"form":"x","cf":"","gw":"","pos":"","lang":"akk","line_ref":"Q003448.21","position":0},{"form":"x","cf":"","gw":"","pos":"","lang":"akk","line_ref":"Q003448.22","position":0},{"form":"{m}tukul-ti-A-e\u2082-\u0161ar\u2082-ra","cf":"Tukulti-apil-E\u0161arra","gw":"Tiglath-pileser III, king of Assyria","pos":"RN","lang":"akk","line_ref":"Q003448.23","position":0},{"form":"GAR","cf":"\u0161aknu","gw":"appointee","pos":"N","lang":"akk","line_ref":"Q003448.23","position":1},{"form":"{d}BAD","cf":"Enlil","gw":"1","pos":"DN","lang":"akk","line_ref":"Q003448.23","position":2},{"form":"NUN","cf":"rub\u00fb","gw":"ruler","pos":"N","lang":"akk","line_ref":"Q003448.23","position":3},{"form":"SANGA","cf":"\u0161ang\u00fb","gw":"priest","pos":"N","lang":"akk","line_ref":"Q003448.23","position":4},{"form":"a\u0161-\u0161ur","cf":"A\u0161\u0161ur","gw":"1","pos":"DN","lang":"akk","line_ref":"Q003448.23","position":5},{"form":"x","cf":"","gw":"","pos":"","lang":"akk","line_ref":"Q003448.24","position":0},{"form":"mu-u\u0161-te-e\u02be-u","cf":"mu\u0161te\u02be\u02be\u00fb","gw":"repeatedly searching//assiduous one","pos":"N$","lang":"akk","line_ref":"Q003448.24","position":1},{"form":"a\u0161\u2082-ri-ku-nu","cf":"a\u0161ru","gw":"place//(divine) abode","pos":"N$a\u0161rikunu","lang":"akk","line_ref":"Q003448.24","position":2},{"form":"ENSI\u2082","cf":"i\u0161\u0161akku","gw":"vice-regent (of a god)","pos":"N","lang":"akk","line_ref":"Q003448.24","position":3},{"form":"x","cf":"","gw":"","pos":"","lang":"akk","line_ref":"Q003448.25","position":0},{"form":"x","cf":"","gw":"","pos":"","lang":"akk","line_ref":"Q003448.25","position":1},{"form":"NUNUZ","cf":"per\u02bei","gw":"offspring","pos":"N","lang":"akk","line_ref":"Q003448.25","position":2},{"form":"{URU}bal-til","cf":"Baltil","gw":"A\u0161\u0161ur","pos":"QN$","lang":"akk","line_ref":"Q003448.25","position":3},{"form":"\u0161u-qu-ru","cf":"\u0161\u016bquru","gw":"very valuable","pos":"AJ","lang":"akk","line_ref":"Q003448.25","position":4},{"form":"x","cf":"","gw":"","pos":"","lang":"akk","line_ref":"Q003448.26","position":0},{"form":"bi-bil\u2082","cf":"biblu","gw":"(action of) bringing//desire","pos":"N$bibil","lang":"akk","line_ref":"Q003448.26","position":1},{"form":"lib\u2083-bi","cf":"libbi","gw":"interior","pos":"N","lang":"akk","line_ref":"Q003448.26","position":2},{"form":"{d}A.EDIN","cf":"\u0160erua","gw":"1","pos":"DN","lang":"akk","line_ref":"Q003448.26","position":3},{"form":"GA\u0160AN","cf":"b\u0113lti","gw":"lady","pos":"N","lang":"akk","line_ref":"Q003448.26","position":4},{"form":"GAL-ti","cf":"rab\u012bti","gw":"great","pos":"AJ","lang":"akk","line_ref":"Q003448.26","position":5},{"form":"x","cf":"","gw":"","pos":"","lang":"akk","line_ref":"Q003448.27","position":0},{"form":"x","cf":"","gw":"","pos":"","lang":"akk","line_ref":"Q003448.27","position":1},{"form":"x","cf":"","gw":"","pos":"","lang":"akk","line_ref":"Q003448.27","position":2},{"form":"SUM","cf":"","gw":"","pos":"","lang":"akk","line_ref":"Q003448.27","position":3},{"form":"ARHU\u0160","cf":"r\u0113mu","gw":"womb//compassion","pos":"N$","lang":"akk","line_ref":"Q003448.27","position":4},{"form":"TUK-\u0161u\u2082","cf":"ra\u0161\u00fb","gw":"obtain//have","pos":"V$ir\u0161i\u0161u","lang":"akk","line_ref":"Q003448.27","position":5},{"form":"NAM.TI.LA","cf":"bal\u0101\u1e6du","gw":"life","pos":"N$","lang":"akk","line_ref":"Q003448.27","position":6},{"form":"x","cf":"","gw":"","pos":"","lang":"akk","line_ref":"Q003448.28","position":0},{"form":"MAN","cf":"\u0161ar","gw":"king","pos":"N","lang":"akk","line_ref":"Q003448.28","position":1},{"form":"ki\u0161-\u0161a\u2082-ti","cf":"ki\u0161\u0161ati","gw":"world","pos":"N","lang":"akk","line_ref":"Q003448.28","position":2},{"form":"MAN","cf":"\u0161ar","gw":"king","pos":"N","lang":"akk","line_ref":"Q003448.28","position":3},{"form":"KUR","cf":"m\u0101t","gw":"land","pos":"N","lang":"akk","line_ref":"Q003448.28","position":4},{"form":"a\u0161-\u0161ur{KI}","cf":"A\u0161\u0161ur","gw":"Assyria","pos":"GN","lang":"akk","line_ref":"Q003448.28","position":5},{"form":"MAN","cf":"\u0161ar","gw":"king","pos":"N","lang":"akk","line_ref":"Q003448.28","position":6},{"form":"KUR","cf":"m\u0101t","gw":"land","pos":"N","lang":"akk","line_ref":"Q003448.28","position":7},{"form":"\u0161u-miri","cf":"\u0160umeru","gw":"Sumer","pos":"GN$\u0160umiri","lang":"akk","line_ref":"Q003448.28","position":8},{"form":"u","cf":"u","gw":"and","pos":"CNJ","lang":"akk","line_ref":"Q003448.29","position":0},{"form":"URI{KI}","cf":"Akkadi","gw":"1","pos":"GN","lang":"akk","line_ref":"Q003448.29","position":1},{"form":"MAN","cf":"\u0161ar","gw":"king","pos":"N","lang":"akk","line_ref":"Q003448.29","position":2},{"form":"kib-rat","cf":"kibr\u0101t","gw":"quarter","pos":"N","lang":"akk","line_ref":"Q003448.29","position":3},{"form":"LIMMU\u2082","cf":"erbetti","gw":"four","pos":"NU","lang":"akk","line_ref":"Q003448.29","position":4},{"form":"SIPA","cf":"r\u0113\u02be\u00fb","gw":"shepherd","pos":"N","lang":"akk","line_ref":"Q003448.29","position":5},{"form":"ba-\u02beu-la-a-tim","cf":"ba\u02be\u016bl\u0101tu","gw":"people","pos":"N$ba\u02be\u016bl\u0101tim","lang":"akk","line_ref":"Q003448.29","position":6},{"form":"GAR","cf":"\u0161\u0101kinu","gw":"one who places","pos":"N$\u0161\u0101kin","lang":"akk","line_ref":"Q003448.30","position":0},{"form":"an-du-ra-ar","cf":"andur\u0101ru","gw":"freedom//exemption","pos":"N$andur\u0101r","lang":"akk","line_ref":"Q003448.30","position":1},{"form":"KUR","cf":"m\u0101t","gw":"land","pos":"N","lang":"akk","line_ref":"Q003448.30","position":2},{"form":"a\u0161-\u0161ur","cf":"A\u0161\u0161ur","gw":"Assyria","pos":"GN","lang":"akk","line_ref":"Q003448.30","position":3},{"form":"mu-\u1e6dib","cf":"mu\u1e6dibbu","gw":"one who pleases","pos":"N$mu\u1e6d\u012bb","lang":"akk","line_ref":"Q003448.30","position":4},{"form":"lib\u2083-bi","cf":"libbi","gw":"heart","pos":"N","lang":"akk","line_ref":"Q003448.30","position":5},{"form":"i\u0161\u2088-tar\u2082","cf":"I\u0161tar","gw":"","pos":"DN$","lang":"akk","line_ref":"Q003448.30","position":6},{"form":"mu-rap-pi\u0161","cf":"murappi\u0161","gw":"one who makes wide","pos":"N","lang":"akk","line_ref":"Q003448.31","position":0},{"form":"mi-\u1e63ir","cf":"mi\u1e63ir","gw":"border","pos":"N","lang":"akk","line_ref":"Q003448.31","position":1},{"form":"KUR","cf":"m\u0101t","gw":"land","pos":"N","lang":"akk","line_ref":"Q003448.31","position":2},{"form":"a\u0161-\u0161ur","cf":"A\u0161\u0161ur","gw":"Assyria","pos":"GN","lang":"akk","line_ref":"Q003448.31","position":3},{"form":"ma-hir","cf":"m\u0101hiru","gw":"opponent//recipient","pos":"N$m\u0101hir","lang":"akk","line_ref":"Q003448.32","position":0},{"form":"GUN","cf":"bilti","gw":"tribute","pos":"N","lang":"akk","line_ref":"Q003448.32","position":1},{"form":"u","cf":"u","gw":"and","pos":"CNJ","lang":"akk","line_ref":"Q003448.32","position":2},{"form":"IGI.SA\u2082-e","cf":"igis\u00ea","gw":"gift","pos":"N","lang":"akk","line_ref":"Q003448.32","position":3},{"form":"\u0161a\u2082","cf":"\u0161a","gw":"of","pos":"DET","lang":"akk","line_ref":"Q003448.32","position":4},{"form":"DU\u2083-\u0161i-na","cf":"kal\u00ee\u0161ina","gw":"all","pos":"N","lang":"akk","line_ref":"Q003448.32","position":5},{"form":"ad-na-ti","cf":"adn\u0101ti","gw":"people","pos":"N","lang":"akk","line_ref":"Q003448.32","position":6},{"form":"x","cf":"","gw":"","pos":"","lang":"akk","line_ref":"Q003448.33","position":0},{"form":"a-na","cf":"ana","gw":"to","pos":"PRP","lang":"akk","line_ref":"Q003448.33","position":1},{"form":"ru-pu-\u0161i","cf":"rap\u0101\u0161u","gw":"be(come) wide//expanding","pos":"V'N$ruppu\u0161i","lang":"akk","line_ref":"Q003448.33","position":2},{"form":"UN.ME\u0160-\u0161a\u2082","cf":"ni\u0161\u012b\u0161a","gw":"people","pos":"N","lang":"akk","line_ref":"Q003448.33","position":3},{"form":"DAGAL.ME\u0160","cf":"rap\u0161\u0101te","gw":"wide","pos":"AJ","lang":"akk","line_ref":"Q003448.33","position":4},{"form":"x","cf":"","gw":"","pos":"","lang":"akk","line_ref":"Q003448.34","position":0},{"form":"a-bur-ri\u0161","cf":"aburri\u0161","gw":"in a green pasture","pos":"AV$","lang":"akk","line_ref":"Q003448.34","position":1},{"form":"a-na","cf":"ana","gw":"to","pos":"PRP","lang":"akk","line_ref":"Q003448.34","position":2},{"form":"re-\u02bee-e","cf":"re\u02be\u00fb","gw":"pasture//shepherding","pos":"V'N$re\u02be\u00ea","lang":"akk","line_ref":"Q003448.34","position":3},{"form":"x","cf":"","gw":"","pos":"","lang":"akk","line_ref":"Q003448.35","position":0},{"form":"i\u0161-ku-un-\u0161u\u2082","cf":"\u0161ak\u0101nu","gw":"put//place","pos":"V$i\u0161kun\u0161u","lang":"akk","line_ref":"Q003448.35","position":1},{"form":"x","cf":"","gw":"","pos":"","lang":"akk","line_ref":"Q003448.36","position":0},{"form":"a\u0161-\u0161ur","cf":"A\u0161\u0161ur","gw":"1","pos":"DN","lang":"akk","line_ref":"Q003448.36","position":1},{"form":"{d}EN.LIL\u2082.LA\u2082","cf":"Enlil","gw":"1","pos":"DN","lang":"akk","line_ref":"Q003448.36","position":2},{"form":"DINGIR.ME\u0160","cf":"il\u0101ni","gw":"god","pos":"N","lang":"akk","line_ref":"Q003448.37","position":0},{"form":"x-du-u","cf":"","gw":"","pos":"","lang":"akk","line_ref":"Q003448.37","position":1},{"form":"a-na","cf":"ana","gw":"to","pos":"PRP","lang":"akk","line_ref":"Q003448.37","position":2},{"form":"\u0161um-qut","cf":"\u0161umqut","gw":"cutting down","pos":"'N","lang":"akk","line_ref":"Q003448.37","position":3},{"form":"la","cf":"l\u0101","gw":"not","pos":"MOD","lang":"akk","line_ref":"Q003448.37","position":4},{"form":"ma-giri","cf":"m\u0101giru","gw":"submissive one","pos":"N$m\u0101gir\u012b","lang":"akk","line_ref":"Q003448.37","position":5},{"form":"u\u2082-\u0161a\u2082-x-x","cf":"","gw":"","pos":"","lang":"akk","line_ref":"Q003448.37","position":6},{"form":"ina","cf":"ina","gw":"at","pos":"PRP","lang":"akk","line_ref":"Q003448.38","position":0},{"form":"SAG","cf":"r\u0113\u0161u","gw":"head//beginning","pos":"N$r\u0113\u0161","lang":"akk","line_ref":"Q003448.38","position":1},{"form":"LUGAL-ti-ia","cf":"\u0161arr\u016btiya","gw":"kingship","pos":"N","lang":"akk","line_ref":"Q003448.38","position":2},{"form":"ina","cf":"ina","gw":"during","pos":"PRP","lang":"akk","line_ref":"Q003448.38","position":3},{"form":"mah-re-e","cf":"mahr\u00ea","gw":"first","pos":"AJ","lang":"akk","line_ref":"Q003448.38","position":4},{"form":"BALA-ia\u2082","cf":"pal\u00fb","gw":"reign (of a king)//regnal year","pos":"N$pal\u00eaya","lang":"akk","line_ref":"Q003448.38","position":5},{"form":"ina","cf":"ina","gw":"during","pos":"PRP","lang":"akk","line_ref":"Q003448.38","position":6},{"form":"6","cf":"","gw":"","pos":"","lang":"akk","line_ref":"Q003448.38","position":7},{"form":"ITI","cf":"arhi","gw":"month","pos":"N","lang":"akk","line_ref":"Q003448.38","position":8},{"form":"\u0161a\u2082","cf":"\u0161a","gw":"that","pos":"REL","lang":"akk","line_ref":"Q003448.38","position":9},{"form":"ina","cf":"ina","gw":"on","pos":"PRP","lang":"akk","line_ref":"Q003448.38","position":10},{"form":"{GI\u0160}GU.ZA","cf":"kuss\u00ee","gw":"throne","pos":"N","lang":"akk","line_ref":"Q003448.38","position":11},{"form":"LUGAL-ti","cf":"\u0161arr\u016bti","gw":"kingship","pos":"N","lang":"akk","line_ref":"Q003448.39","position":0},{"form":"ra-bi\u0161","cf":"rab\u00ee\u0161","gw":"magnificently","pos":"AV","lang":"akk","line_ref":"Q003448.39","position":1},{"form":"u\u2082-\u0161i-bu","cf":"\u016b\u0161ibu","gw":"sit","pos":"V","lang":"akk","line_ref":"Q003448.39","position":2},{"form":"ERIM.HI.A-at","cf":"umm\u0101nu","gw":"military force//troops","pos":"N$umm\u0101n\u0101t","lang":"akk","line_ref":"Q003448.39","position":3},{"form":"KUR","cf":"m\u0101t","gw":"land","pos":"N","lang":"akk","line_ref":"Q003448.39","position":4},{"form":"a\u0161-\u0161ur{KI}","cf":"A\u0161\u0161ur","gw":"Assyria","pos":"GN","lang":"akk","line_ref":"Q003448.39","position":5},{"form":"gap-\u0161a\u2082-a-ti","cf":"gap\u0161u","gw":"arisen","pos":"AJ$gap\u0161\u0101ti","lang":"akk","line_ref":"Q003448.39","position":6},{"form":"lu","cf":"l\u016b","gw":"may","pos":"MOD","lang":"akk","line_ref":"Q003448.40","position":0},{"form":"ad-ke","cf":"dek\u00fb","gw":"raise//muster","pos":"V$adke","lang":"akk","line_ref":"Q003448.40","position":1},{"form":"x","cf":"","gw":"","pos":"","lang":"akk","line_ref":"Q003448.40","position":2},{"form":"x","cf":"","gw":"","pos":"","lang":"akk","line_ref":"Q003448.42","position":0},{"form":"U\u2082","cf":"","gw":"","pos":"","lang":"akk","line_ref":"Q003448.42","position":1},{"form":"x","cf":"","gw":"","pos":"","lang":"akk","line_ref":"Q003448.42","position":2},{"form":"KUR","cf":"","gw":"","pos":"","lang":"akk","line_ref":"Q003448.42","position":3},{"form":"x","cf":"","gw":"","pos":"","lang":"akk","line_ref":"Q003448.43","position":0},{"form":"pa-a","cf":"p\u00e2","gw":"mouth","pos":"N","lang":"akk","line_ref":"Q003448.43","position":1},{"form":"1-en","cf":"i\u0161t\u0113n","gw":"one","pos":"NU","lang":"akk","line_ref":"Q003448.43","position":2},{"form":"u\u2082-\u0161a\u2082-a\u0161\u2082-kin\u2082-\u0161u-nu-ti","cf":"\u0161ak\u0101nu","gw":"put//have established","pos":"V$u\u0161a\u0161kin\u0161un\u016bti","lang":"akk","line_ref":"Q003448.44","position":0},{"form":"a-na","cf":"ana","gw":"to","pos":"PRP","lang":"akk","line_ref":"Q003448.44","position":1},{"form":"KUR","cf":"m\u0101t","gw":"land","pos":"N","lang":"akk","line_ref":"Q003448.44","position":2},{"form":"a\u0161-\u0161ur","cf":"A\u0161\u0161ur","gw":"Assyria","pos":"GN","lang":"akk","line_ref":"Q003448.44","position":3},{"form":"u\u2082-ra-a\u0161\u2082-\u0161u\u2082-nu-ti","cf":"war\u00fb","gw":"lead","pos":"V$\u016br\u00e2\u0161\u0161un\u016bti","lang":"akk","line_ref":"Q003448.44","position":4},{"form":"x","cf":"","gw":"","pos":"","lang":"akk","line_ref":"Q003448.45","position":0},{"form":"{LU\u2082}\u0161u-ut","cf":"\u0161\u016bt","gw":"who(m)","pos":"DET","lang":"akk","line_ref":"Q003448.45","position":1},{"form":"SAG-ia","cf":"r\u0113\u0161iya","gw":"head","pos":"N","lang":"akk","line_ref":"Q003448.45","position":2},{"form":"ina","cf":"ina","gw":"on","pos":"PRP","lang":"akk","line_ref":"Q003448.45","position":3},{"form":"UGU-\u0161u\u2082-nu","cf":"muhhu","gw":"skull","pos":"N$muhhi\u0161unu","lang":"akk","line_ref":"Q003448.45","position":4},{"form":"GAR-un","cf":"\u0161ak\u0101nu","gw":"put//place","pos":"$a\u0161kun +.","lang":"akk","line_ref":"Q003448.45","position":5},{"form":"ina","cf":"ina","gw":"during","pos":"PRP","lang":"akk","line_ref":"Q003448.46","position":0},{"form":"2","cf":"","gw":"","pos":"","lang":"akk","line_ref":"Q003448.46","position":1},{"form":"BALA-ia","cf":"pal\u00eaya","gw":"regnal year","pos":"N","lang":"akk","line_ref":"Q003448.46","position":2},{"form":"ana","cf":"ana","gw":"to","pos":"PRP","lang":"akk","line_ref":"Q003448.46","position":3},{"form":"{KUR}ZALAG\u2082","cf":"Namri","gw":"","pos":"GN$","lang":"akk","line_ref":"Q003448.46","position":4},{"form":"{KUR}E\u2082-si-in-gi-bu-ti","cf":"Bit-Sangibuti","gw":"","pos":"GN$Bit-Singibuti","lang":"akk","line_ref":"Q003448.46","position":5},{"form":"lu","cf":"l\u016b","gw":"may","pos":"MOD","lang":"akk","line_ref":"Q003448.46","position":6},{"form":"al-lik","cf":"allik","gw":"go","pos":"V","lang":"akk","line_ref":"Q003448.46","position":7},{"form":"x","cf":"","gw":"","pos":"","lang":"akk","line_ref":"Q003448.47","position":0},{"form":"{KUR}E\u2082-{m}bar-ru-a","cf":"Bit-Barrua","gw":"1","pos":"GN","lang":"akk","line_ref":"Q003448.47","position":1},{"form":"x","cf":"","gw":"","pos":"","lang":"akk","line_ref":"Q003448.48","position":0},{"form":"x","cf":"","gw":"","pos":"","lang":"akk","line_ref":"Q003448.48","position":1},{"form":"qu","cf":"","gw":"","pos":"","lang":"akk","line_ref":"Q003448.48","position":2},{"form":"\u0161a\u2082","cf":"\u0161a","gw":"of","pos":"DET","lang":"akk","line_ref":"Q003448.48","position":3},{"form":"x","cf":"","gw":"","pos":"","lang":"akk","line_ref":"Q003448.48","position":4},{"form":"MAL","cf":"","gw":"","pos":"","lang":"akk","line_ref":"Q003448.48","position":5},{"form":"x","cf":"","gw":"","pos":"","lang":"akk","line_ref":"Q003448.48","position":6},{"form":"x","cf":"","gw":"","pos":"","lang":"akk","line_ref":"Q003448.48","position":7},{"form":"x","cf":"","gw":"","pos":"","lang":"akk","line_ref":"Q003448.48","position":8},{"form":"x","cf":"","gw":"","pos":"","lang":"akk","line_ref":"Q003448.48","position":9},{"form":"E\u0160","cf":"","gw":"","pos":"","lang":"akk","line_ref":"Q003448.48","position":10},{"form":"x-ti-ia\u2082","cf":"","gw":"","pos":"","lang":"akk","line_ref":"Q003448.48","position":11},{"form":"x","cf":"","gw":"","pos":"","lang":"akk","line_ref":"Q003448.49","position":0},{"form":"BA-\u0161a\u2082-ni","cf":"qi\u0101\u0161u","gw":"give","pos":"V$iq\u012b\u0161anni","lang":"akk","line_ref":"Q003448.49","position":1},{"form":"ina","cf":"ina","gw":"with","pos":"PRP","lang":"akk","line_ref":"Q003448.49","position":2},{"form":"{GI\u0160}TUKUL","cf":"kakki","gw":"weapon","pos":"N","lang":"akk","line_ref":"Q003448.49","position":3},{"form":"u\u2082-\u0161am-qit","cf":"maq\u0101tu","gw":"fall down//cut down","pos":"V$u\u0161amqit","lang":"akk","line_ref":"Q003448.49","position":4},{"form":"\u0161al-la-su-nu","cf":"\u0161allassunu","gw":"booty","pos":"N","lang":"akk","line_ref":"Q003448.49","position":5},{"form":"a\u0161\u2082-lu-la","cf":"a\u0161lula","gw":"carry off","pos":"V","lang":"akk","line_ref":"Q003448.50","position":0},{"form":"{LU\u2082}\u0161u-ut","cf":"\u0161\u016bt","gw":"who(m)","pos":"DET","lang":"akk","line_ref":"Q003448.50","position":1},{"form":"SAG-ia","cf":"r\u0113\u0161iya","gw":"head","pos":"N","lang":"akk","line_ref":"Q003448.50","position":2},{"form":"ina","cf":"ina","gw":"on","pos":"PRP","lang":"akk","line_ref":"Q003448.50","position":3},{"form":"UGU","cf":"muhhi","gw":"skull","pos":"N","lang":"akk","line_ref":"Q003448.50","position":4},{"form":"{KUR}par-su-a","cf":"Parsua","gw":"","pos":"GN$","lang":"akk","line_ref":"Q003448.50","position":5},{"form":"{LU\u2082}\u0161u-ut","cf":"\u0161\u016bt","gw":"who(m)","pos":"DET","lang":"akk","line_ref":"Q003448.51","position":0},{"form":"SAG-ia\u2082","cf":"r\u0113\u0161u","gw":"head","pos":"N$r\u0113\u0161iya","lang":"akk","line_ref":"Q003448.51","position":1},{"form":"ina","cf":"ina","gw":"on","pos":"PRP","lang":"akk","line_ref":"Q003448.51","position":2},{"form":"UGU","cf":"muhhi","gw":"skull","pos":"N","lang":"akk","line_ref":"Q003448.51","position":3},{"form":"{KUR}E\u2082-ha-am-ban","cf":"Bit-Hamban","gw":"1","pos":"GN","lang":"akk","line_ref":"Q003448.51","position":4},{"form":"GAR-un","cf":"\u0161ak\u0101nu","gw":"put//place","pos":"V$a\u0161kun","lang":"akk","line_ref":"Q003448.51","position":5},{"form":"KUR.KUR","cf":"m\u0101t\u0101ti","gw":"land","pos":"N","lang":"akk","line_ref":"Q003448.51","position":6},{"form":"\u0161u-a-ti-na","cf":"\u0161u\u0101tina","gw":"those","pos":"IP","lang":"akk","line_ref":"Q003448.51","position":7},{"form":"a-na","cf":"ana","gw":"to","pos":"PRP","lang":"akk","line_ref":"Q003448.52","position":0},{"form":"BULUG-ki","cf":"pulukku","gw":"boundary marker//boundary","pos":"N$pulukki","lang":"akk","line_ref":"Q003448.52","position":1},{"form":"KUR","cf":"m\u0101t","gw":"land","pos":"N","lang":"akk","line_ref":"Q003448.52","position":2},{"form":"a\u0161-\u0161ur","cf":"A\u0161\u0161ur","gw":"Assyria","pos":"GN","lang":"akk","line_ref":"Q003448.52","position":3},{"form":"GUR-er","cf":"t\u00e2ru","gw":"turn//return","pos":"V$ut\u0113r +.","lang":"akk","line_ref":"Q003448.52","position":4},{"form":"ma-da-tu\u2082","cf":"maddattu","gw":"payment","pos":"N$","lang":"akk","line_ref":"Q003448.52","position":5},{"form":"\u0161a\u2082","cf":"\u0161a","gw":"of","pos":"DET","lang":"akk","line_ref":"Q003448.52","position":6},{"form":"{m}dal-ta-a","cf":"Dalta","gw":"king of Ellipi","pos":"RN","lang":"akk","line_ref":"Q003448.52","position":7},{"form":"{KUR}e-lip\u2082-a-a","cf":"Ellipayu","gw":"of Ellipi","pos":"EN$Ellipaya","lang":"akk","line_ref":"Q003448.52","position":8},{"form":"{LU\u2082}EN.URU.ME\u0160","cf":"b\u0113lu","gw":"lord","pos":"N$b\u0113l&\u0101lu[city","lang":"akk","line_ref":"Q003448.53","position":0},{"form":"{LU\u2082}EN.URU.ME\u0160","cf":"b\u0113lu","gw":"lord","pos":"N$b\u0113l&\u0101lu[city","lang":"akk","line_ref":"Q003448.53","position":1},{"form":"\u0161a\u2082","cf":"\u0161a","gw":"of","pos":"DET","lang":"akk","line_ref":"Q003448.53","position":2},{"form":"{KUR}ZALAG\u2082","cf":"Namri","gw":"","pos":"GN$","lang":"akk","line_ref":"Q003448.53","position":3},{"form":"{KUR}sin-gi-bu-te","cf":"Bit-Sangibuti","gw":"","pos":"GN$Singibute","lang":"akk","line_ref":"Q003448.53","position":4},{"form":"mada-a-a","cf":"Madayu","gw":"Median","pos":"EN$Madaya","lang":"akk","line_ref":"Q003448.53","position":5},{"form":"\u0161a\u2082","cf":"\u0161a","gw":"of","pos":"DET","lang":"akk","line_ref":"Q003448.53","position":6},{"form":"KUR-e","cf":"\u0161ad\u00ea","gw":"mountain","pos":"N","lang":"akk","line_ref":"Q003448.53","position":7},{"form":"DU\u2083-\u0161u\u2082-nu","cf":"kal\u00ee\u0161unu","gw":"all","pos":"N","lang":"akk","line_ref":"Q003448.53","position":8},{"form":"\u0161a\u2082","cf":"\u0161a","gw":"of","pos":"DET","lang":"akk","line_ref":"Q003448.54","position":0},{"form":"KUR","cf":"nipih","gw":"rising","pos":"N","lang":"akk","line_ref":"Q003448.54","position":1},{"form":"\u0161am-\u0161i","cf":"\u0161am\u0161u","gw":"sun","pos":"N$\u0161am\u0161i","lang":"akk","line_ref":"Q003448.54","position":2},{"form":"AN\u0160E.KUR.RA.ME\u0160","cf":"sis\u00ea","gw":"horse","pos":"N","lang":"akk","line_ref":"Q003448.54","position":3},{"form":"{AN\u0160E}pa-re-e","cf":"par\u00ea","gw":"mule","pos":"N","lang":"akk","line_ref":"Q003448.54","position":4},{"form":"LAL-at","cf":"\u1e63imittu","gw":"binding//(yoke-)team","pos":"N$\u1e63imdat","lang":"akk","line_ref":"Q003448.54","position":5},{"form":"{GI\u0160}ni-ri","cf":"n\u012bru","gw":"yoke","pos":"N$n\u012bri","lang":"akk","line_ref":"Q003448.54","position":6},{"form":"{AN\u0160E}ud-ra-te","cf":"udr\u0101te","gw":"Bactrian camel","pos":"N","lang":"akk","line_ref":"Q003448.55","position":0},{"form":"GU\u2084.ME\u0160","cf":"alp\u012b","gw":"ox","pos":"N","lang":"akk","line_ref":"Q003448.55","position":1},{"form":"u","cf":"u","gw":"and","pos":"CNJ","lang":"akk","line_ref":"Q003448.55","position":2},{"form":"\u1e63e-e-ni","cf":"\u1e63\u0113n\u012b","gw":"sheep and goats","pos":"N","lang":"akk","line_ref":"Q003448.55","position":3},{"form":"a-na","cf":"ana","gw":"for","pos":"PRP","lang":"akk","line_ref":"Q003448.55","position":4},{"form":"la","cf":"l\u0101","gw":"not","pos":"MOD","lang":"akk","line_ref":"Q003448.55","position":5},{"form":"mi\u2083-ni","cf":"m\u012bni","gw":"number","pos":"N","lang":"akk","line_ref":"Q003448.55","position":6},{"form":"am-hur","cf":"amhur","gw":"receive","pos":"V +.","lang":"akk","line_ref":"Q003448.55","position":7},{"form":"ina","cf":"ina","gw":"during","pos":"PRP","lang":"akk","line_ref":"Q003448.56","position":0},{"form":"ta-a-a-ar-ti-ia\u2082","cf":"tayyartu","gw":"return","pos":"N$tayyartiya","lang":"akk","line_ref":"Q003448.56","position":1},{"form":"{m}ir-an-su","cf":"Iranzi","gw":"king of Mannea","pos":"RN$Iransu","lang":"akk","line_ref":"Q003448.56","position":2},{"form":"{KUR}ma-na-a-a","cf":"Mannayu","gw":"Mannean","pos":"EN$Mannaya","lang":"akk","line_ref":"Q003448.56","position":3},{"form":"qur-di","cf":"qurd\u012b","gw":"heroism","pos":"N","lang":"akk","line_ref":"Q003448.56","position":4},{"form":"ta-nit-te","cf":"tanittu","gw":"praise","pos":"N$tanitte","lang":"akk","line_ref":"Q003448.56","position":5},{"form":"\u0161a\u2082","cf":"\u0161a","gw":"of","pos":"DET","lang":"akk","line_ref":"Q003448.57","position":0},{"form":"a\u0161-\u0161ur","cf":"A\u0161\u0161ur","gw":"1","pos":"DN","lang":"akk","line_ref":"Q003448.57","position":1},{"form":"EN-ia\u2082","cf":"b\u0113liya","gw":"lord","pos":"N","lang":"akk","line_ref":"Q003448.57","position":2},{"form":"\u0161a\u2082","cf":"\u0161a","gw":"that","pos":"REL","lang":"akk","line_ref":"Q003448.57","position":3},{"form":"a-na","cf":"ana","gw":"to","pos":"PRP","lang":"akk","line_ref":"Q003448.57","position":4},{"form":"EN.URU.ME\u0160","cf":"b\u0113lu","gw":"lord","pos":"N$b\u0113l&\u0101lu[city","lang":"akk","line_ref":"Q003448.57","position":5},{"form":"EN.URU.ME\u0160","cf":"b\u0113lu","gw":"lord","pos":"N$b\u0113l&\u0101lu[city","lang":"akk","line_ref":"Q003448.57","position":6},{"form":"\u0161a\u2082","cf":"\u0161a","gw":"of","pos":"DET","lang":"akk","line_ref":"Q003448.57","position":7},{"form":"KUR-e","cf":"\u0161ad\u00ea","gw":"mountain","pos":"N","lang":"akk","line_ref":"Q003448.57","position":8},{"form":"DU\u2083-\u0161u\u2082-nu","cf":"kal\u00ee\u0161unu","gw":"all","pos":"N","lang":"akk","line_ref":"Q003448.57","position":9},{"form":"A\u2082-pu-\u0161a\u2082","cf":"ep\u0113\u0161u","gw":"do","pos":"V$\u0113teppu\u0161\u0101","lang":"akk","line_ref":"Q003448.57","position":10},{"form":"i\u0161-me-ma","cf":"i\u0161mema","gw":"hear","pos":"V","lang":"akk","line_ref":"Q003448.57","position":11},{"form":"hur-ba-\u0161u\u2082","cf":"hurb\u0101\u0161u","gw":"terror","pos":"N","lang":"akk","line_ref":"Q003448.58","position":0},{"form":"UGU-\u0161u\u2082","cf":"eli\u0161u","gw":"over","pos":"PRP","lang":"akk","line_ref":"Q003448.58","position":1},{"form":"it-ta-bi-ik-ma","cf":"tab\u0101ku","gw":"heap up//pour","pos":"V$ittabikma","lang":"akk","line_ref":"Q003448.58","position":2},{"form":"a-na","cf":"ana","gw":"to","pos":"PRP","lang":"akk","line_ref":"Q003448.58","position":3},{"form":"{URU}su-um-bi","cf":"Sumbi","gw":"","pos":"GN'SN$","lang":"akk","line_ref":"Q003448.58","position":4},{"form":"i-te-e","cf":"it\u00ea","gw":"boundary","pos":"N","lang":"akk","line_ref":"Q003448.58","position":5},{"form":"KUR","cf":"m\u0101t","gw":"land","pos":"N","lang":"akk","line_ref":"Q003448.58","position":6},{"form":"a\u0161-\u0161ur{KI}","cf":"A\u0161\u0161ur","gw":"Assyria","pos":"GN","lang":"akk","line_ref":"Q003448.58","position":7},{"form":"a-di","cf":"adi","gw":"to","pos":"PRP","lang":"akk","line_ref":"Q003448.59","position":0},{"form":"mah-ri-ia","cf":"mahriya","gw":"front","pos":"N","lang":"akk","line_ref":"Q003448.59","position":1},{"form":"DU-ka-am-ma","cf":"al\u0101ku","gw":"go","pos":"V$illikamma","lang":"akk","line_ref":"Q003448.59","position":2},{"form":"u\u2082-na-\u0161i-qa","cf":"na\u0161\u0101qu","gw":"kiss","pos":"V$una\u0161\u0161iqa","lang":"akk","line_ref":"Q003448.59","position":3},{"form":"GIR\u2083.II-ia\u2082","cf":"\u0161\u0113p\u012bya","gw":"foot","pos":"N","lang":"akk","line_ref":"Q003448.59","position":4},{"form":"AN\u0160E.KUR.RA.ME\u0160","cf":"sis\u00ea","gw":"horse","pos":"N","lang":"akk","line_ref":"Q003448.59","position":5},{"form":"BABBAR.ME\u0160","cf":"pe\u1e63\u00fbti","gw":"white","pos":"AJ","lang":"akk","line_ref":"Q003448.60","position":0},{"form":"GUN\u2083.ME\u0160","cf":"birmu","gw":"multicoloured","pos":"AJ$birm\u016bti","lang":"akk","line_ref":"Q003448.60","position":1},{"form":"har-\u0161a\u2082-a-a","cf":"Har\u0161aya","gw":"of Har\u0161u","pos":"EN","lang":"akk","line_ref":"Q003448.60","position":2},{"form":"har-x","cf":"","gw":"","pos":"","lang":"akk","line_ref":"Q003448.60","position":3},{"form":"UZU-\u0161u\u2082-nu","cf":"\u0161\u012bru","gw":"flesh//skin","pos":"N$\u0161\u012br\u0161unu","lang":"akk","line_ref":"Q003448.60","position":4},{"form":"a-di","cf":"adi","gw":"with","pos":"PRP","lang":"akk","line_ref":"Q003448.60","position":5},{"form":"ta-lul-ti-\u0161u\u2082-nu","cf":"tallultu","gw":"trappings","pos":"N$tallulti\u0161unu","lang":"akk","line_ref":"Q003448.60","position":6},{"form":"x","cf":"","gw":"","pos":"","lang":"akk","line_ref":"Q003448.60","position":7},{"form":"x","cf":"","gw":"","pos":"","lang":"akk","line_ref":"Q003448.60","position":8},{"form":"GU\u2084.MAH.ME\u0160","cf":"gum\u0101h\u012b","gw":"prize bull","pos":"N","lang":"akk","line_ref":"Q003448.61","position":0},{"form":"MAH.ME\u0160","cf":"\u1e63\u012br\u016bti","gw":"exalted","pos":"AJ","lang":"akk","line_ref":"Q003448.61","position":1},{"form":"\u0161u-\u02bee-e","cf":"\u0161\u00fb","gw":"sheep","pos":"N$\u0161u\u02be\u0113","lang":"akk","line_ref":"Q003448.61","position":2},{"form":"ma-ru-u-ti","cf":"mar\u00fb","gw":"fattened","pos":"AJ$mar\u00fbti","lang":"akk","line_ref":"Q003448.61","position":3},{"form":"ma","cf":"","gw":"","pos":"","lang":"akk","line_ref":"Q003448.61","position":4},{"form":"x","cf":"","gw":"","pos":"","lang":"akk","line_ref":"Q003448.61","position":5},{"form":"x","cf":"","gw":"","pos":"","lang":"akk","line_ref":"Q003448.61","position":6},{"form":"x-da","cf":"","gw":"","pos":"","lang":"akk","line_ref":"Q003448.61","position":7},{"form":"x-\u0161u\u2082","cf":"","gw":"","pos":"","lang":"akk","line_ref":"Q003448.61","position":8},{"form":"am-hur","cf":"amhur","gw":"receive","pos":"V +.","lang":"akk","line_ref":"Q003448.61","position":9},{"form":"ina","cf":"ina","gw":"during","pos":"PRP","lang":"akk","line_ref":"Q003448.62","position":0},{"form":"3-\u0161i","cf":"","gw":"","pos":"","lang":"akk","line_ref":"Q003448.62","position":1},{"form":"BALA-ia\u2082","cf":"pal\u00fb","gw":"reign (of a king)//regnal year","pos":"N$pal\u00eaya","lang":"akk","line_ref":"Q003448.62","position":2},{"form":"{m}ma-ti-il\u2083","cf":"Mati\u02be-il","gw":"king of Arpad","pos":"RN$","lang":"akk","line_ref":"Q003448.62","position":3},{"form":"DUMU","cf":"m\u0101r","gw":"son","pos":"N","lang":"akk","line_ref":"Q003448.62","position":4},{"form":"{m}a-tar-\u0161um\u2082-qa","cf":"Attar-\u0161umki","gw":"ruler of Arpad","pos":"RN$Attar-\u0161umqa","lang":"akk","line_ref":"Q003448.62","position":5},{"form":"bar-tu","cf":"b\u0101rtu","gw":"revolt","pos":"N$","lang":"akk","line_ref":"Q003448.62","position":6},{"form":"na-bal-kat-tu\u2082","cf":"nabalkattu","gw":"crossing//insurrection","pos":"N$","lang":"akk","line_ref":"Q003448.62","position":7},{"form":"a-na","cf":"ana","gw":"to","pos":"PRP","lang":"akk","line_ref":"Q003448.63","position":0},{"form":"KUR","cf":"m\u0101t","gw":"land","pos":"N","lang":"akk","line_ref":"Q003448.63","position":1},{"form":"a\u0161-\u0161ur","cf":"A\u0161\u0161ur","gw":"Assyria","pos":"GN","lang":"akk","line_ref":"Q003448.63","position":2},{"form":"DU\u2083-ma","cf":"\u0113pu\u0161ma","gw":"make","pos":"V","lang":"akk","line_ref":"Q003448.63","position":3},{"form":"u\u2082-ha-\u1e6da-a","cf":"ha\u1e6d\u00fb","gw":"do wrong//violate","pos":"V$uha\u1e6d\u1e6d\u00e2","lang":"akk","line_ref":"Q003448.63","position":4},{"form":"x","cf":"","gw":"","pos":"","lang":"akk","line_ref":"Q003448.63","position":5},{"form":"LUGAL.ME\u0160","cf":"\u0161arr\u0101ni","gw":"king","pos":"N","lang":"akk","line_ref":"Q003448.63","position":6},{"form":"\u0161a\u2082","cf":"\u0161a","gw":"who","pos":"REL","lang":"akk","line_ref":"Q003448.63","position":7},{"form":"a-na","cf":"ana","gw":"to","pos":"PRP","lang":"akk","line_ref":"Q003448.63","position":8},{"form":"x","cf":"","gw":"","pos":"","lang":"akk","line_ref":"Q003448.63","position":9},{"form":"x.ME\u0160","cf":"","gw":"","pos":"","lang":"akk","line_ref":"Q003448.63","position":10},{"form":"\u0161a","cf":"\u0161a","gw":"of","pos":"DET","lang":"akk","line_ref":"Q003448.63","position":11},{"form":"{KUR}hat-ti","cf":"Hatti","gw":"Syria-Palestine","pos":"GN","lang":"akk","line_ref":"Q003448.63","position":12},{"form":"x","cf":"","gw":"","pos":"","lang":"akk","line_ref":"Q003448.64","position":0},{"form":"ud","cf":"","gw":"","pos":"","lang":"akk","line_ref":"Q003448.64","position":1},{"form":"a","cf":"","gw":"","pos":"","lang":"akk","line_ref":"Q003448.64","position":2},{"form":"ku","cf":"","gw":"","pos":"","lang":"akk","line_ref":"Q003448.64","position":3},{"form":"{KUR}URI","cf":"Urar\u1e6di","gw":"1","pos":"GN","lang":"akk","line_ref":"Q003448.64","position":4},{"form":"ze-rat","cf":"z\u0113r\u0101t","gw":"hostilities","pos":"N","lang":"akk","line_ref":"Q003448.64","position":5},{"form":"KUR","cf":"m\u0101t","gw":"land","pos":"N","lang":"akk","line_ref":"Q003448.64","position":6},{"form":"a\u0161-\u0161ur","cf":"A\u0161\u0161ur","gw":"Assyria","pos":"GN","lang":"akk","line_ref":"Q003448.64","position":7},{"form":"x-ma","cf":"","gw":"","pos":"","lang":"akk","line_ref":"Q003448.64","position":8},{"form":"u\u2082-\u0161am-ki-ir","cf":"nak\u0101ru","gw":"be(come) different//cause enmity between","pos":"V$u\u0161amkir","lang":"akk","line_ref":"Q003448.64","position":9},{"form":"ma-ti-tan","cf":"m\u0101tit\u0101n","gw":"in all lands","pos":"'AV","lang":"akk","line_ref":"Q003448.64","position":10},{"form":"{m}{d}INANNA-du-ri","cf":"I\u0161tar-duri","gw":"Sarduri, king of Urar\u1e6du","pos":"RN$I\u0161tar-duri","lang":"akk","line_ref":"Q003448.65","position":0},{"form":"{KUR}URI-a-a","cf":"Urar\u1e6daya","gw":"of Urar\u1e6du","pos":"EN","lang":"akk","line_ref":"Q003448.65","position":1},{"form":"{m}su-lu-ma-al","cf":"Sulumal","gw":"king of Melid","pos":"RN","lang":"akk","line_ref":"Q003448.65","position":2},{"form":"{KUR}me-li-da-a-a","cf":"Meliddayu","gw":"of Melid","pos":"EN$Melidaya","lang":"akk","line_ref":"Q003448.65","position":3},{"form":"{m}tar-qu\u2082-la-ru","cf":"Tarhu-lara","gw":"king of Gurgum","pos":"RN$Tarqu-laru","lang":"akk","line_ref":"Q003448.65","position":4},{"form":"{KUR}gur\u2082-gu-ma-a-a","cf":"Gurgumaya","gw":"of Gurgum","pos":"EN","lang":"akk","line_ref":"Q003448.66","position":0},{"form":"a-na","cf":"ana","gw":"to","pos":"PRP","lang":"akk","line_ref":"Q003448.66","position":1},{"form":"kit-ri-\u0161u\u2082","cf":"kitru","gw":"help","pos":"N$kitri\u0161u","lang":"akk","line_ref":"Q003448.66","position":2},{"form":"il-li-ku","cf":"illik\u016b","gw":"go","pos":"V","lang":"akk","line_ref":"Q003448.66","position":3},{"form":"i-na","cf":"ina","gw":"in","pos":"PRP","lang":"akk","line_ref":"Q003448.66","position":4},{"form":"bi-rit","cf":"bir\u012bt","gw":"between","pos":"PRP$","lang":"akk","line_ref":"Q003448.66","position":5},{"form":"{KUR}ki\u0161-tan","cf":"Ki\u0161tan","gw":"","pos":"GN$","lang":"akk","line_ref":"Q003448.66","position":6},{"form":"u","cf":"u","gw":"and","pos":"CNJ","lang":"akk","line_ref":"Q003448.66","position":7},{"form":"{KUR}hal-pi","cf":"Halpi","gw":"","pos":"GN$","lang":"akk","line_ref":"Q003448.66","position":8},{"form":"na-ge-e","cf":"nag\u00ea","gw":"region","pos":"N","lang":"akk","line_ref":"Q003448.67","position":0},{"form":"\u0161a","cf":"\u0161a","gw":"of","pos":"DET","lang":"akk","line_ref":"Q003448.67","position":1},{"form":"{KUR}ku-muh-hi","cf":"Kummuhu","gw":"","pos":"GN$Kummuhi","lang":"akk","line_ref":"Q003448.67","position":2},{"form":"a-na","cf":"ana","gw":"to","pos":"PRP","lang":"akk","line_ref":"Q003448.67","position":3},{"form":"e-muq","cf":"em\u016bq","gw":"strength","pos":"N","lang":"akk","line_ref":"Q003448.67","position":4},{"form":"a-ha-me\u0161","cf":"ah\u0101me\u0161","gw":"one another","pos":"RP","lang":"akk","line_ref":"Q003448.67","position":5},{"form":"it-tak-lu-ma","cf":"ittakl\u016bma","gw":"trust","pos":"V","lang":"akk","line_ref":"Q003448.67","position":6},{"form":"i\u0161-kunu","cf":"\u0161ak\u0101nu","gw":"put//establish","pos":"V$i\u0161kun\u016b","lang":"akk","line_ref":"Q003448.68","position":0},{"form":"si-dir-tu\u2082","cf":"sidirtu","gw":"row//line of battle","pos":"N$ +.","lang":"akk","line_ref":"Q003448.68","position":1},{"form":"7","cf":"","gw":"","pos":"","lang":"akk","line_ref":"Q003448.68","position":2},{"form":"KASKAL.GID\u2082","cf":"b\u0113ru","gw":"double hour","pos":"N","lang":"akk","line_ref":"Q003448.68","position":3},{"form":"qaq-qa-ru","cf":"qaqqaru","gw":"distance","pos":"N","lang":"akk","line_ref":"Q003448.68","position":4},{"form":"GE\u2086","cf":"m\u016b\u0161u","gw":"night","pos":"N$","lang":"akk","line_ref":"Q003448.68","position":5},{"form":"u","cf":"u","gw":"and","pos":"CNJ","lang":"akk","line_ref":"Q003448.68","position":6},{"form":"ur-ru","cf":"urru","gw":"day","pos":"N$","lang":"akk","line_ref":"Q003448.68","position":7},{"form":"al-li-ka-am-ma","cf":"al\u0101ku","gw":"go","pos":"V$allikamma","lang":"akk","line_ref":"Q003448.69","position":0},{"form":"ERIM.HI.A-at","cf":"umm\u0101nu","gw":"military force//troops","pos":"N$umm\u0101n\u0101t","lang":"akk","line_ref":"Q003448.69","position":1},{"form":"KUR","cf":"m\u0101t","gw":"land","pos":"N","lang":"akk","line_ref":"Q003448.69","position":2},{"form":"a\u0161-\u0161ur{KI}","cf":"A\u0161\u0161ur","gw":"Assyria","pos":"GN","lang":"akk","line_ref":"Q003448.69","position":3},{"form":"ul","cf":"ul","gw":"not","pos":"MOD","lang":"akk","line_ref":"Q003448.69","position":4},{"form":"u\u2082-\u0161ap-\u0161i-ih-ma","cf":"pa\u0161\u0101hu","gw":"be(come) at rest//allow to rest","pos":"V$u\u0161ap\u0161ihma","lang":"akk","line_ref":"Q003448.69","position":5},{"form":"A.ME\u0160","cf":"m\u00ea","gw":"water","pos":"N","lang":"akk","line_ref":"Q003448.70","position":0},{"form":"ul","cf":"ul","gw":"not","pos":"MOD","lang":"akk","line_ref":"Q003448.70","position":1},{"form":"a\u0161\u2082-qi\u2082","cf":"\u0161aq\u00fb","gw":"give to drink//give (drink) to","pos":"V$a\u0161qi","lang":"akk","line_ref":"Q003448.70","position":2},{"form":"u\u0161-ma-ni","cf":"u\u0161mann\u012b","gw":"camp","pos":"N","lang":"akk","line_ref":"Q003448.70","position":3},{"form":"ul","cf":"ul","gw":"not","pos":"MOD","lang":"akk","line_ref":"Q003448.70","position":4},{"form":"GAR-un-ma","cf":"\u0161ak\u0101nu","gw":"put//establish","pos":"V$a\u0161kunma","lang":"akk","line_ref":"Q003448.70","position":5},{"form":"ul","cf":"ul","gw":"not","pos":"MOD","lang":"akk","line_ref":"Q003448.70","position":6},{"form":"ak-\u1e63u-ra","cf":"ka\u1e63\u0101ru","gw":"tie//construct","pos":"V$ak\u1e63ura","lang":"akk","line_ref":"Q003448.70","position":7},{"form":"KARA\u0160-\u0161i","cf":"kar\u0101\u0161u","gw":"military camp","pos":"N$kar\u0101\u0161i","lang":"akk","line_ref":"Q003448.71","position":0},{"form":"ERIM.HI.A-ia","cf":"umm\u0101n\u0101tiya","gw":"troops","pos":"N","lang":"akk","line_ref":"Q003448.71","position":1},{"form":"an-hu-su-nu","cf":"anh\u016btu","gw":"tiredness","pos":"N$anh\u016bssunu","lang":"akk","line_ref":"Q003448.71","position":2},{"form":"TA-\u0161u\u2082-nu","cf":"itti","gw":"with","pos":"PRP$itti\u0161unu","lang":"akk","line_ref":"Q003448.71","position":3},{"form":"am-da-hi-i\u1e63","cf":"amdahi\u1e63","gw":"fight","pos":"V","lang":"akk","line_ref":"Q003448.71","position":4},{"form":"BAD\u2085.BAD\u2085-\u0161u\u2082-nu","cf":"dabd\u00fb","gw":"defeat","pos":"N$dabd\u00e2\u0161unu","lang":"akk","line_ref":"Q003448.72","position":0},{"form":"GAR-un","cf":"a\u0161kun","gw":"establish","pos":"V","lang":"akk","line_ref":"Q003448.72","position":1},{"form":"u\u0161-ma-ni","cf":"u\u0161mannu","gw":"camp","pos":"N$u\u0161manni","lang":"akk","line_ref":"Q003448.72","position":2},{"form":"KARA\u0160-su-nu","cf":"kar\u0101\u0161u","gw":"military camp","pos":"N$kar\u0101ssunu","lang":"akk","line_ref":"Q003448.72","position":3},{"form":"e-kim-\u0161u\u2082-nu-ti","cf":"\u0113kim\u0161un\u016bti","gw":"take away","pos":"V +.","lang":"akk","line_ref":"Q003448.72","position":4},{"form":"a-na","cf":"ana","gw":"to","pos":"PRP","lang":"akk","line_ref":"Q003448.73","position":0},{"form":"\u0161u-zu-ub","cf":"\u0161\u016bzub","gw":"saving","pos":"'N","lang":"akk","line_ref":"Q003448.73","position":1},{"form":"ZI.ME\u0160-\u0161u-nu","cf":"napi\u0161tu","gw":"throat//life","pos":"N$nap\u0161\u0101ti\u0161unu","lang":"akk","line_ref":"Q003448.73","position":2},{"form":"ZAH\u2082.ME\u0160-ma","cf":"hal\u0101qu","gw":"be(come) lost//escape","pos":"V$ihliq\u016bma","lang":"akk","line_ref":"Q003448.73","position":3},{"form":"{m}{d}15-BAD\u2083","cf":"I\u0161tar-duri","gw":"Sarduni, king of Urar\u1e6du","pos":"RN$I\u0161tar-duri","lang":"akk","line_ref":"Q003448.74","position":0},{"form":"{KUR}URI-a-a","cf":"Urar\u1e6daya","gw":"of Urar\u1e6du","pos":"EN","lang":"akk","line_ref":"Q003448.74","position":1},{"form":"e-de-nu-u\u0161-\u0161u","cf":"\u0113d\u0113nu\u0161\u0161u","gw":"alone","pos":"AV","lang":"akk","line_ref":"Q003448.74","position":2},{"form":"ina","cf":"ina","gw":"on","pos":"PRP","lang":"akk","line_ref":"Q003448.74","position":3},{"form":"MUNUS.AN\u0160E.KUR.RA","cf":"ur\u012btu","gw":"mare","pos":"N$ur\u012bti","lang":"akk","line_ref":"Q003448.74","position":4},{"form":"U\u2085-ma","cf":"rak\u0101bu","gw":"ride","pos":"V$irkamma","lang":"akk","line_ref":"Q003448.74","position":5},{"form":"GE\u2086-i\u0161","cf":"m\u016b\u0161i\u0161","gw":"at night","pos":"AV$","lang":"akk","line_ref":"Q003448.75","position":0},{"form":"ip-pa\u2082-ri\u0161-ma","cf":"napru\u0161u","gw":"fly","pos":"V$ippari\u0161ma","lang":"akk","line_ref":"Q003448.75","position":1},{"form":"x","cf":"","gw":"","pos":"","lang":"akk","line_ref":"Q003448.75","position":2},{"form":"x","cf":"","gw":"","pos":"","lang":"akk","line_ref":"Q003448.75","position":3},{"form":"\u0161e","cf":"","gw":"","pos":"","lang":"akk","line_ref":"Q003448.75","position":4},{"form":"ir","cf":"","gw":"","pos":"","lang":"akk","line_ref":"Q003448.75","position":5},{"form":"x","cf":"","gw":"","pos":"","lang":"akk","line_ref":"Q003448.75","position":6},{"form":"\u0161a\u2082","cf":"\u0161a","gw":"who","pos":"REL","lang":"akk","line_ref":"Q003448.76","position":0},{"form":"ki-i","cf":"k\u012b","gw":"like","pos":"PRP","lang":"akk","line_ref":"Q003448.76","position":1},{"form":"pa-\u0161ul-ti","cf":"pa\u0161ultu","gw":"(a crawling creature)","pos":"N$pa\u0161ulti","lang":"akk","line_ref":"Q003448.76","position":2},{"form":"x","cf":"","gw":"","pos":"","lang":"akk","line_ref":"Q003448.76","position":3},{"form":"a-na","cf":"ana","gw":"to","pos":"PRP","lang":"akk","line_ref":"Q003448.76","position":4},{"form":"x","cf":"","gw":"","pos":"","lang":"akk","line_ref":"Q003448.76","position":5},{"form":"pa-qut-ti","cf":"puquttu","gw":"thorn","pos":"N$paqutti","lang":"akk","line_ref":"Q003448.77","position":0},{"form":"ed-de-ti","cf":"eddittu","gw":"(a kind of thorn-bush)","pos":"N$edd\u0113ti","lang":"akk","line_ref":"Q003448.77","position":1},{"form":"mu-\u0161ah\u2082-x","cf":"","gw":"","pos":"","lang":"akk","line_ref":"Q003448.77","position":2},{"form":"x","cf":"","gw":"","pos":"","lang":"akk","line_ref":"Q003448.77","position":3},{"form":"ip-\u0161il-ma","cf":"pa\u0161\u0101lu","gw":"crawl","pos":"V$ip\u0161ilma","lang":"akk","line_ref":"Q003448.78","position":0},{"form":"e-li","cf":"\u0113li","gw":"ascend","pos":"V","lang":"akk","line_ref":"Q003448.78","position":1},{"form":"a-na","cf":"ana","gw":"to","pos":"PRP","lang":"akk","line_ref":"Q003448.78","position":2},{"form":"KUR-\u0161u\u2082","cf":"m\u0101ti\u0161u","gw":"land","pos":"N","lang":"akk","line_ref":"Q003448.78","position":3},{"form":"GUR-ur","cf":"t\u00e2ru","gw":"turn//return","pos":"V$it\u016br +.","lang":"akk","line_ref":"Q003448.78","position":4},{"form":"TA","cf":"ultu","gw":"from","pos":"PRP","lang":"akk","line_ref":"Q003448.78","position":5},{"form":"{URU}hu-ti-x","cf":"","gw":"","pos":"","lang":"akk","line_ref":"Q003448.78","position":6},{"form":"at-tu-mu\u0161","cf":"nam\u0101\u0161u","gw":"set (oneself) in motion","pos":"V$attumu\u0161","lang":"akk","line_ref":"Q003448.78","position":7},{"form":"1","cf":"","gw":"","pos":"","lang":"akk","line_ref":"Q003448.79","position":0},{"form":"ME","cf":"m\u0113","gw":"(one) hundred","pos":"NU","lang":"akk","line_ref":"Q003448.79","position":1},{"form":"URU.ME\u0160","cf":"\u0101l\u0101ni","gw":"city","pos":"N","lang":"akk","line_ref":"Q003448.79","position":2},{"form":"\u0161a\u2082","cf":"\u0161a","gw":"of","pos":"DET","lang":"akk","line_ref":"Q003448.79","position":3},{"form":"{m}tar-hu-la-ri","cf":"Tarhu-lara","gw":"king of Gurgum","pos":"RN$Tarhu-lari","lang":"akk","line_ref":"Q003448.79","position":4},{"form":"{KUR}gur\u2082-gu-ma-a-a","cf":"Gurgumaya","gw":"of Gurgum","pos":"EN","lang":"akk","line_ref":"Q003448.79","position":5},{"form":"ak-tu\u2082-um","cf":"kat\u0101mu","gw":"cover","pos":"V$aktum","lang":"akk","line_ref":"Q003448.79","position":6},{"form":"x","cf":"","gw":"","pos":"","lang":"akk","line_ref":"Q003448.79","position":7},{"form":"a-di","cf":"adi","gw":"with","pos":"PRP","lang":"akk","line_ref":"Q003448.80","position":0},{"form":"URU.ME\u0160","cf":"\u0101l\u0101ni","gw":"city","pos":"N","lang":"akk","line_ref":"Q003448.80","position":1},{"form":"\u0161a\u2082","cf":"\u0161a","gw":"of","pos":"DET","lang":"akk","line_ref":"Q003448.80","position":2},{"form":"si-hir-ti-\u0161u\u2082-nu","cf":"sihirti\u0161unu","gw":"surroundings","pos":"N","lang":"akk","line_ref":"Q003448.80","position":3},{"form":"KUR-ud","cf":"ak\u0161ud","gw":"conquer","pos":"V","lang":"akk","line_ref":"Q003448.80","position":4},{"form":"{m}tar-hu-la-ri","cf":"Tarhu-lara","gw":"king of Gurgum","pos":"RN$Tarhu-lari","lang":"akk","line_ref":"Q003448.80","position":5},{"form":"x","cf":"","gw":"","pos":"","lang":"akk","line_ref":"Q003448.80","position":6},{"form":"a-di","cf":"adi","gw":"with","pos":"PRP","lang":"akk","line_ref":"Q003448.81","position":0},{"form":"SAG.KAL.ME\u0160","cf":"a\u0161ar\u0113du","gw":"first and foremost one//official","pos":"N'N$a\u0161ar\u0113d\u016bti","lang":"akk","line_ref":"Q003448.81","position":1},{"form":"\u0161a","cf":"\u0161a","gw":"of","pos":"DET","lang":"akk","line_ref":"Q003448.81","position":2},{"form":"KUR-\u0161u\u2082","cf":"m\u0101ti\u0161u","gw":"land","pos":"N","lang":"akk","line_ref":"Q003448.81","position":3},{"form":"it-ti","cf":"itti","gw":"with","pos":"PRP","lang":"akk","line_ref":"Q003448.81","position":4},{"form":"ku-dur-ru-\u0161u\u2082-nu","cf":"kudurru","gw":"carrying frame","pos":"N$kudurru\u0161unu","lang":"akk","line_ref":"Q003448.81","position":5}]}